Workbook

Sheet 0_v31改動與假設
A1: 聯茂 6213｜v31 損益模型 改動與假設
A2: 基準版本：v30（20260818）｜本版觸發：Wallace 裁示拆出獨立 M9 線＋重建可見驅動引擎｜建立日：2026-08-18
A4: 一、本版三項改動
A5: 項目 | B5: v30 | C5: v31 | D5: 影響 | E5: 依據／說明
A6: ① 重建可見驅動引擎 | B6: 無（僅損益表） | C6: 1_營收驅動 分頁 | D6: 可稽核／可重現 | E6: v29/v30 的 xlsx 只有損益表，資料夾內無 build script 或 config，模型已不可重現。本版把產能／稼動率／組合／價格指數／售價全部寫回分頁。
A7: ② M9 自 M8 桶拆出 | B7: M8以上＝M7×0.20，單一指數 2.37 | C7: M9 獨立線，量佔比 2%（2027年均），指數 8.00，毛利率 50% | D7: 2027 GM +1.72pp | E7: ★Wallace 裁示（價格指數來自板廠，準確性高）。原做法把 M9 與 M8 併桶用 2.37，低於 M8 自身的 3.00，等於把 M9 當成比 M8 便宜的東西算；且 M9 無獨立放量曲線。法說：台光電 M9 為 3Q26 出貨、聯茂落後兩季→1Q27 起，「明年初才少量放量」，M9 毛利率「至少 50% 起」。
A8: ③ M8/M8U 係數與指數 | B8: M7×0.20，指數 2.37，GM 49% | C8: M7×0.12，指數 3.00，GM 48% | D8: — | E8: 原 0.20 為 M8＋M9 合計；M9 抽出後降至 0.12。指數改用價格指數表的 M8 真值 3.00。
A9: ④ 售價路徑改為由營收錨點反解 | B9: 外生給定 | C9: 內生反解 | D9: 營收不變 | E9: ★v28 驅動 Note 第 36~37 列已載明：「26Q3 售價漲幅 15% 是由 Rev QoQ +25% guidance 反解，混合 ASP +24.6% 中純售價 15%、其餘為 mix」。組合升級已包在營收 guidance 內，若加 M9 而不同步下修售價即為重複計算。本版鎖住營收錨點（＝v30／公司 guidance），讓 M9 只改毛利率與 ASP 組成。
A11: 二、★ 已揭露的內部矛盾（Wallace 20260818 裁示接受）
A12: 三個錨點無法同時滿足：(a) 營收貼公司 guidance (b) M9 量佔比 2% × 指數 8.0 (c) 0813「E-glass 緩解後價格不回落」。
A13: 本版選擇保留 (a)(b)，犧牲 (c)：模型隱含的「純售價」在 2H27 為 27Q2 −1.5%／27Q3 −4.1%／27Q4 −5.3%，2028 亦為小幅負值。
A14: 若改採 (c) 而放開營收，2027 營收將達 1,236 億（YoY +129%）、EPS 69.79，遠超公司「至少三四十的 YoY 成長」指引，故不採為主案。
A15: → 追蹤點：若 2027 實際售價確實未回落而營收超標，代表 M9 貢獻被低估，須上修；反之若售價回落，本版路徑即被驗證。
A17: 三、分流比與單耗：為什麼沒有改成 70%
A18: 公司說「CCL 約占營收 7 成、PP 約 3 成」是【營收口徑】；模型的分流比 57.1% 是【面積／張數口徑】（海關單批 700 張：PP 300 張/99.28㎡ vs CCL 400 張/132.38㎡）。
A19: CCL＝PP＋兩面銅箔＋壓合，單位面積售價高於 PP。設倍數 k：CCL 營收佔比 ＝ 0.571k/(0.571k+0.429) ＝ 70% → k ＝ 1.75。銅箔佔 CCL 材料成本 40%，1.75 倍完全合理。
A20: → 兩個數字互相印證，不是矛盾。把分流比改成 70% 等於把價格效應重複計入數量方程式。
A21: ★ 更根本：M7 張數 ＝ mPPO 噸 × r ÷ u，只有比值 r/u ＝ 3,037 張/噸 被資料釘住，r 與 u 各自不可分辨（not separately identified）。
A22: 改 r＝0.70 就必須同步改 u＝0.2305 才能維持同樣張數，模型輸出一格不動。而 0.188 本身也是反解值，非量測值。
A23: → 唯一能真正改善這一格的，是取得 r 或 u 之一的獨立一手數據：跟公司要「M7 每月出貨張數的絕對值」（開放清單第 2 項）。
A25: 四、級距價格指數與毛利率（藍字＝可調輸入）
A26: 級距 | B26: 價格指數 | C26: 級距毛利率 | D26: 來源
A27: FR4/M2 | B27: 0.48 | C27: 0.25 | D27: 指數：Wallace 提供（板廠資料）｜毛利率：0815「M4 以下現在應有 25%」
A28: M4 | B28: 0.75 | C28: 0.25 | D28: 同上
A29: M6 | B29: 1 | C29: 0.35 | D29: 指數基準＝1.00｜0813「M6 已由過往約 30% 提高至 35% 以上」
A30: M7 | B30: 1.3 | C30: 0.4 | D30: 0813「M7 由約 35% 提高至至少 40%」
A31: M8/M8U | B31: 3 | C31: 0.48 | D31: ★v31 改用價格指數表 M8 真值 3.00（v30 為併桶值 2.37）
A32: M9 | B32: 8 | C32: 0.5 | D32: ★v31 新增獨立線。指數 8.00 為 Wallace 裁示（板廠表列 17.00，本版取保守值）｜0815「M9 至少 50% 起跳」
A34: M8/M8U 量佔比係數（相對 M7） | B34: 0.12 | D34: v30 為 0.20（含 M9）；M9 抽出後降至 0.12｜Wallace 20260818 確認
A35: mPPO CCL 分流比 r | B35: 0.571 | D35: ⚠️ 與 u 不可分辨，只有 r/u 有意義。見第三節。
A36: 每張 M7 CCL 耗用 u（kg） | B36: 0.188 | D36: 反解值：由「M6以上 30%」＋「年底 M7 >10%」交叉反解，非量測值

Sheet 1_營收驅動
A1: 營收驅動：產能 × 稼動率 × 六級距組合
A2: 單位 | B2: 26Q1 | C2: 26Q2 | D2: 26Q3 | E2: 26Q4 | F2: 27Q1 | G2: 27Q2 | H2: 27Q3 | I2: 27Q4 | J2: 28Q1 | K2: 28Q2 | L2: 28Q3 | M2: 28Q4
A3: 月產能（萬張/月） | B3: 540 | C3: 540 | D3: 540 | E3: 555 | F3: 590 | G3: 620 | H3: 630 | I3: 630 | J3: 630 | K3: 690 | L3: 765 | M3: 810 | O3: 公司公告；2028 已後移一季（v30）
A4: 稼動率 | B4: 0.7358 | C4: 0.7444 | D4: 0.77 | E4: 0.775 | F4: 0.78 | G4: 0.8 | H4: 0.88 | I4: 0.95 | J4: 0.9 | K4: 0.9 | L4: 0.9 | M4: 0.9 | O4: 0813：26Q4 75~80%；2027 年底視布源可能近 100%
A5: 季產出（萬張） | B5: =B3*3*B4 -> 1191.996 | C5: =C3*3*C4 -> 1205.928 | D5: =D3*3*D4 -> 1247.4 | E5: =E3*3*E4 -> 1290.375 | F5: =F3*3*F4 -> 1380.6 | G5: =G3*3*G4 -> 1488 | H5: =H3*3*H4 -> 1663.2 | I5: =I3*3*I4 -> 1795.5 | ... M5: =M3*3*M4 -> 2187
A6: mPPO 交聯茂（噸/季） | B6: 20 | C6: 40 | D6: 160 | E6: 256 | F6: 290 | G6: 320 | H6: 350 | I6: 375 | J6: 400 | K6: 430 | L6: 455 | M6: 475
A7: M7 CCL 出貨（萬張） | B7: =B6*0_v31改動與假設!$B$35*1000/0_v31改動與假設!$B$36/10000 -> 6.0744681 | C7: =C6*0_v31改動與假設!$B$35*1000/0_v31改動與假設!$B$36/10000 -> 12.148936 | D7: =D6*0_v31改動與假設!$B$35*1000/0_v31改動與假設!$B$36/10000 -> 48.595745 | E7: =E6*0_v31改動與假設!$B$35*1000/0_v31改動與假設!$B$36/10000 -> 77.753191 | F7: =F6*0_v31改動與假設!$B$35*1000/0_v31改動與假設!$B$36/10000 -> 88.079787 | G7: =G6*0_v31改動與假設!$B$35*1000/0_v31改動與假設!$B$36/10000 -> 97.191489 | H7: =H6*0_v31改動與假設!$B$35*1000/0_v31改動與假設!$B$36/10000 -> 106.30319 | I7: =I6*0_v31改動與假設!$B$35*1000/0_v31改動與假設!$B$36/10000 -> 113.89628 | ... M7: =M6*0_v31改動與假設!$B$35*1000/0_v31改動與假設!$B$36/10000 -> 144.26862
A8: —— 量佔比（佔季產出張數）
A9: 量佔比 M4 | B9: 0.21 | C9: 0.21 | D9: 0.205 | E9: 0.2 | F9: 0.195 | G9: 0.19 | H9: 0.185 | I9: 0.18 | J9: 0.175 | K9: 0.172 | L9: 0.17 | M9: 0.168
A10: 量佔比 M6（反解） | B10: 0.140485 | C10: 0.174975 | D10: 0.160612 | E10: 0.17756 | F10: 0.158764 | G10: 0.138025 | H10: 0.125656 | I10: 0.103793 | J10: 0.099514 | K10: 0.110785 | L10: 0.121278 | M10: 0.13543 | O10: ★由「M6以上營收佔比」錨點反解，見下方檢核列
A11: 量佔比 M7 | B11: =B7/B5 -> 0.0050960474 | C11: =C7/C5 -> 0.010074346 | D11: =D7/D5 -> 0.038957628 | E11: =E7/E5 -> 0.060256275 | F11: =F7/F5 -> 0.063798194 | G11: =G7/G5 -> 0.065316861 | H11: =H7/H5 -> 0.063914858 | I11: =I7/I5 -> 0.063434295 | ... M11: =M7/M5 -> 0.065966446
A12: 量佔比 M8/M8U | B12: =B11*0_v31改動與假設!$B$34 -> 0.00061152568 | C12: =C11*0_v31改動與假設!$B$34 -> 0.0012089215 | D12: =D11*0_v31改動與假設!$B$34 -> 0.0046749153 | E12: =E11*0_v31改動與假設!$B$34 -> 0.0072307531 | F12: =F11*0_v31改動與假設!$B$34 -> 0.0076557833 | G12: =G11*0_v31改動與假設!$B$34 -> 0.0078380233 | H12: =H11*0_v31改動與假設!$B$34 -> 0.0076697829 | I12: =I11*0_v31改動與假設!$B$34 -> 0.0076121154 | ... M12: =M11*0_v31改動與假設!$B$34 -> 0.0079159735
A13: 量佔比 M9 ★新增 | B13: 0 | C13: 0 | D13: 0 | E13: 0 | F13: 0.008 | G13: 0.016 | H13: 0.024 | I13: 0.032 | J13: 0.035 | K13: 0.038 | L13: 0.042 | M13: 0.045 | O13: ★Wallace 裁示：2027 年均 2.0%，1Q27 起爬坡
A14: 量佔比 FR4/M2（殘差） | B14: =1-B9-B10-B11-B12-B13 -> 0.64380743 | C14: =1-C9-C10-C11-C12-C13 -> 0.60374173 | D14: =1-D9-D10-D11-D12-D13 -> 0.59075546 | E14: =1-E9-E10-E11-E12-E13 -> 0.55495297 | F14: =1-F9-F10-F11-F12-F13 -> 0.56678202 | G14: =1-G9-G10-G11-G12-G13 -> 0.58282012 | H14: =1-H9-H10-H11-H12-H13 -> 0.59375936 | I14: =1-I9-I10-I11-I12-I13 -> 0.61316059 | ... M14: =1-M9-M10-M11-M12-M13 -> 0.57768758
A15: 混合價格指數 | B15: =B14*0_v31改動與假設!$B$27+B9*0_v31改動與假設!$B$28+B10*0_v31改動與假設!$B$29+B11*0_v31改動與假設!$B$30+B12*0_v31改動與假設!$B$31+B13*0_v31改動與假設!$B$32 -> 0.615472 | C15: =C14*0_v31改動與假設!$B$27+C9*0_v31改動與假設!$B$28+C10*0_v31改動與假設!$B$29+C11*0_v31改動與假設!$B$30+C12*0_v31改動與假設!$B$31+C13*0_v31改動與假設!$B$32 -> 0.63899445 | D15: =D14*0_v31改動與假設!$B$27+D9*0_v31改動與假設!$B$28+D10*0_v31改動與假設!$B$29+D11*0_v31改動與假設!$B$30+D12*0_v31改動與假設!$B$31+D13*0_v31改動與假設!$B$32 -> 0.66259428 | E15: =E14*0_v31改動與假設!$B$27+E9*0_v31改動與假設!$B$28+E10*0_v31改動與假設!$B$29+E11*0_v31改動與假設!$B$30+E12*0_v31改動與假設!$B$31+E13*0_v31改動與假設!$B$32 -> 0.69396284 | F15: =F14*0_v31改動與假設!$B$27+F9*0_v31改動與假設!$B$28+F10*0_v31改動與假設!$B$29+F11*0_v31改動與假設!$B$30+F12*0_v31改動與假設!$B$31+F13*0_v31改動與假設!$B$32 -> 0.74697437 | G15: =G14*0_v31改動與假設!$B$27+G9*0_v31改動與假設!$B$28+G10*0_v31改動與假設!$B$29+G11*0_v31改動與假設!$B$30+G12*0_v31改動與假設!$B$31+G13*0_v31改動與假設!$B$32 -> 0.79670464 | H15: =H14*0_v31改動與假設!$B$27+H9*0_v31改動與假設!$B$28+H10*0_v31改動與假設!$B$29+H11*0_v31改動與假設!$B$30+H12*0_v31改動與假設!$B$31+H13*0_v31改動與假設!$B$32 -> 0.84750916 | I15: =I14*0_v31改動與假設!$B$27+I9*0_v31改動與假設!$B$28+I10*0_v31改動與假設!$B$29+I11*0_v31改動與假設!$B$30+I12*0_v31改動與假設!$B$31+I13*0_v31改動與假設!$B$32 -> 0.89441101 | ... M15: =M14*0_v31改動與假設!$B$27+M9*0_v31改動與假設!$B$28+M10*0_v31改動與假設!$B$29+M11*0_v31改動與假設!$B$30+M12*0_v31改動與假設!$B$31+M13*0_v31改動與假設!$B$32 -> 1.0082243
A16: M6 基準價（元/張，反解） | B16: 1246.2515 | C16: 1496.2731 | D16: 1743.4536 | E16: 1981.6364 | F16: 1988.805 | G16: 1958.0822 | H16: 1877.0168 | I16: 1778.1144 | J16: 1820.4039 | K16: 1770.1362 | L16: 1696.704 | M16: 1632.0277 | O16: ★由營收錨點反解，非外生給定。見改動說明④
A17: 純售價 QoQ | B17: — | C17: =C16/B16-1 -> 0.2006189 | D17: =D16/C16-1 -> 0.16519745 | E17: =E16/D16-1 -> 0.13661551 | F17: =F16/E16-1 -> 0.0036175153 | G17: =G16/F16-1 -> -0.015447869 | H17: =H16/G16-1 -> -0.041400407 | I17: =I16/H16-1 -> -0.052691271 | J17: =J16/I16-1 -> 0.02378334 | ... M17: =M16/L16-1 -> -0.038118788 | O17: ⚠️ 2H27 為負值＝已揭露的內部矛盾，見改動說明第二節
A18: 混合 ASP（元/張） | B18: =B15*B16 -> 767.03291 | C18: =C15*C16 -> 956.1102 | D18: =D15*D16 -> 1155.2024 | E18: =E15*E16 -> 1375.182 | F18: =F15*F16 -> 1485.5864 | G18: =G15*G16 -> 1560.0132 | H18: =H15*H16 -> 1590.7889 | I18: =I15*I16 -> 1590.3651 | ... M18: =M15*M16 -> 1645.45
A19: 季營收（億元） | B19: =B5*10000*B18/100000000 -> 91.430016 | C19: =C5*10000*C18/100000000 -> 115.30001 | D19: =D5*10000*D18/100000000 -> 144.09995 | E19: =E5*10000*E18/100000000 -> 177.45005 | F19: =F5*10000*F18/100000000 -> 205.10005 | G19: =G5*10000*G18/100000000 -> 232.12996 | H19: =H5*10000*H18/100000000 -> 264.58001 | I19: =I5*10000*I18/100000000 -> 285.55005 | ... M19: =M5*10000*M18/100000000 -> 359.85993
A20: 季毛利率 | B20: =0.1142 -> 0.1142 | C20: =0.2202 -> 0.2202 | D20: =(D14*0_v31改動與假設!$B$27*0_v31改動與假設!$C$27+D9*0_v31改動與假設!$B$28*0_v31改動與假設!$C$28+D10*0_v31改動與假設!$B$29*0_v31改動與假設!$C$29+D11*0_v31改動與假設!$B$30*0_v31改動與假設!$C$30+D12*0_v31改動與假設!$B$31*0_v31改動與假設!$C$31+D13*0_v31改動與假設!$B$32*0_v31改動與假設!$C$32)/D15 -> 0.29057329 | E20: =(E14*0_v31改動與假設!$B$27*0_v31改動與假設!$C$27+E9*0_v31改動與假設!$B$28*0_v31改動與假設!$C$28+E10*0_v31改動與假設!$B$29*0_v31改動與假設!$C$29+E11*0_v31改動與假設!$B$30*0_v31改動與假設!$C$30+E12*0_v31改動與假設!$B$31*0_v31改動與假設!$C$31+E13*0_v31改動與假設!$B$32*0_v31改動與假設!$C$32)/E15 -> 0.29970755 | F20: =(F14*0_v31改動與假設!$B$27*0_v31改動與假設!$C$27+F9*0_v31改動與假設!$B$28*0_v31改動與假設!$C$28+F10*0_v31改動與假設!$B$29*0_v31改動與假設!$C$29+F11*0_v31改動與假設!$B$30*0_v31改動與假設!$C$30+F12*0_v31改動與假設!$B$31*0_v31改動與假設!$C$31+F13*0_v31改動與假設!$B$32*0_v31改動與假設!$C$32)/F15 -> 0.31640059 | G20: =(G14*0_v31改動與假設!$B$27*0_v31改動與假設!$C$27+G9*0_v31改動與假設!$B$28*0_v31改動與假設!$C$28+G10*0_v31改動與假設!$B$29*0_v31改動與假設!$C$29+G11*0_v31改動與假設!$B$30*0_v31改動與假設!$C$30+G12*0_v31改動與假設!$B$31*0_v31改動與假設!$C$31+G13*0_v31改動與假設!$B$32*0_v31改動與假設!$C$32)/G15 -> 0.33026503 | H20: =(H14*0_v31改動與假設!$B$27*0_v31改動與假設!$C$27+H9*0_v31改動與假設!$B$28*0_v31改動與假設!$C$28+H10*0_v31改動與假設!$B$29*0_v31改動與假設!$C$29+H11*0_v31改動與假設!$B$30*0_v31改動與假設!$C$30+H12*0_v31改動與假設!$B$31*0_v31改動與假設!$C$31+H13*0_v31改動與假設!$B$32*0_v31改動與假設!$C$32)/H15 -> 0.34241333 | I20: =(I14*0_v31改動與假設!$B$27*0_v31改動與假設!$C$27+I9*0_v31改動與假設!$B$28*0_v31改動與假設!$C$28+I10*0_v31改動與假設!$B$29*0_v31改動與假設!$C$29+I11*0_v31改動與假設!$B$30*0_v31改動與假設!$C$30+I12*0_v31改動與假設!$B$31*0_v31改動與假設!$C$31+I13*0_v31改動與假設!$B$32*0_v31改動與假設!$C$32)/I15 -> 0.35286249 | J20: =(J14*0_v31改動與假設!$B$27*0_v31改動與假設!$C$27+J9*0_v31改動與假設!$B$28*0_v31改動與假設!$C$28+J10*0_v31改動與假設!$B$29*0_v31改動與假設!$C$29+J11*0_v31改動與假設!$B$30*0_v31改動與假設!$C$30+J12*0_v31改動與假設!$B$31*0_v31改動與假設!$C$31+J13*0_v31改動與假設!$B$32*0_v31改動與假設!$C$32)/J15 -> 0.35819239 | K20: =(K14*0_v31改動與假設!$B$27*0_v31改動與假設!$C$27+K9*0_v31改動與假設!$B$28*0_v31改動與假設!$C$28+K10*0_v31改動與假設!$B$29*0_v31改動與假設!$C$29+K11*0_v31改動與假設!$B$30*0_v31改動與假設!$C$30+K12*0_v31改動與假設!$B$31*0_v31改動與假設!$C$31+K13*0_v31改動與假設!$B$32*0_v31改動與假設!$C$32)/K15 -> 0.36233945 | ... M20: =(M14*0_v31改動與假設!$B$27*0_v31改動與假設!$C$27+M9*0_v31改動與假設!$B$28*0_v31改動與假設!$C$28+M10*0_v31改動與假設!$B$29*0_v31改動與假設!$C$29+M11*0_v31改動與假設!$B$30*0_v31改動與假設!$C$30+M12*0_v31改動與假設!$B$31*0_v31改動與假設!$C$31+M13*0_v31改動與假設!$B$32*0_v31改動與假設!$C$32)/M15 -> 0.37087437 | O20: 26Q1/Q2 為實績；26Q3 起由級距毛利率加權
A21: —— 輸出與檢核
A22: M6 以上 營收佔比 | B22: =(B10*0_v31改動與假設!$B$29+B11*0_v31改動與假設!$B$30+B12*0_v31改動與假設!$B$31+B13*0_v31改動與假設!$B$32)/B15 -> 0.24200035 | C22: =(C10*0_v31改動與假設!$B$29+C11*0_v31改動與假設!$B$30+C12*0_v31改動與假設!$B$31+C13*0_v31改動與假設!$B$32)/C15 -> 0.30000013 | D22: =(D10*0_v31改動與假設!$B$29+D11*0_v31改動與假設!$B$30+D12*0_v31改動與假設!$B$31+D13*0_v31改動與假設!$B$32)/D15 -> 0.33999941 | E22: =(E10*0_v31改動與假設!$B$29+E11*0_v31改動與假設!$B$30+E12*0_v31改動與假設!$B$31+E13*0_v31改動與假設!$B$32)/E15 -> 0.4000004 | F22: =(F10*0_v31改動與假設!$B$29+F11*0_v31改動與假設!$B$30+F12*0_v31改動與假設!$B$31+F13*0_v31改動與假設!$B$32)/F15 -> 0.44000037 | G22: =(G10*0_v31改動與假設!$B$29+G11*0_v31改動與假設!$B$30+G12*0_v31改動與假設!$B$31+G13*0_v31改動與假設!$B$32)/G15 -> 0.46999976 | H22: =(H10*0_v31改動與假設!$B$29+H11*0_v31改動與假設!$B$30+H12*0_v31改動與假設!$B$31+H13*0_v31改動與假設!$B$32)/H15 -> 0.5000001 | I22: =(I10*0_v31改動與假設!$B$29+I11*0_v31改動與假設!$B$30+I12*0_v31改動與假設!$B$31+I13*0_v31改動與假設!$B$32)/I15 -> 0.52000023 | ... M22: =(M10*0_v31改動與假設!$B$29+M11*0_v31改動與假設!$B$30+M12*0_v31改動與假設!$B$31+M13*0_v31改動與假設!$B$32)/M15 -> 0.5999997
A23: M9 營收佔比 | B23: =B13*0_v31改動與假設!$B$32/B15 -> 0 | C23: =C13*0_v31改動與假設!$B$32/C15 -> 0 | D23: =D13*0_v31改動與假設!$B$32/D15 -> 0 | E23: =E13*0_v31改動與假設!$B$32/E15 -> 0 | F23: =F13*0_v31改動與假設!$B$32/F15 -> 0.085678977 | G23: =G13*0_v31改動與假設!$B$32/G15 -> 0.1606618 | H23: =H13*0_v31改動與假設!$B$32/H15 -> 0.22654622 | I23: =I13*0_v31改動與假設!$B$32/I15 -> 0.28622188 | ... M23: =M13*0_v31改動與假設!$B$32/M15 -> 0.35706339
A24: 錨點：M6以上營收佔比目標 | B24: 0.242 | C24: 0.3 | D24: 0.34 | E24: 0.4 | F24: 0.44 | G24: 0.47 | H24: 0.5 | I24: 0.52 | J24: 0.54 | K24: 0.56 | L24: 0.58 | M24: 0.6
A25: 錨點：季營收目標（v30） | B25: 91.43 | C25: 115.3 | D25: 144.1 | E25: 177.45 | F25: 205.1 | G25: 232.13 | H25: 264.58 | I25: 285.55 | J25: 285.61 | K25: 312.79 | L25: 343.41 | M25: 359.86
A26: 檢核① 組合（應為 0） | B26: =B22-B24 -> 3.4733616e-07 | C26: =C22-C24 -> 1.2652074e-07 | D26: =D22-D24 -> -5.9430829e-07 | E26: =E22-E24 -> 4.0329698e-07 | F26: =F22-F24 -> 3.727688e-07 | G26: =G22-G24 -> -2.4305392e-07 | H26: =H22-H24 -> 1.011768e-07 | I26: =I22-I24 -> 2.2701624e-07 | ... M26: =M22-M24 -> -3.0073266e-07
A27: 檢核② 營收（應為 0） | B27: =B19-B25 -> 1.5779877e-05 | C27: =C19-C25 -> 6.2313722e-06 | D27: =D19-D25 -> -5.4501445e-05 | E27: =E19-E25 -> 5.1344757e-05 | F27: =F19-F25 -> 5.4069953e-05 | G27: =G19-G25 -> -3.8235729e-05 | H27: =H19-H25 -> 1.3956463e-05 | I27: =I19-I25 -> 5.3907777e-05 | ... M27: =M19-M25 -> -7.4343266e-05

Sheet 2_月度損益表
A1: 單位：億元 | B1: 115/01 | C1: 115/02 | D1: 115/03 | E1: 115/04 | F1: 115/05 | G1: 115/06 | H1: 115/07 | I1: 115/08 | J1: 115/09 | K1: 115/10 | L1: 115/11 | M1: 115/12 | N1: 116/01 | O1: 116/02 | P1: 116/03 | Q1: 116/04 | R1: 116/05 | S1: 116/06 | T1: 116/07 | U1: 116/08 | V1: 116/09 | W1: 116/10 | X1: 116/11 | Y1: 116/12 | Z1: 117/01 | AA1: 117/02 | AB1: 117/03 | AC1: 117/04 | AD1: 117/05 | AE1: 117/06 | AF1: 117/07 | AG1: 117/08 | AH1: 117/09 | AI1: 117/10 | AJ1: 117/11 | AK1: 117/12 | AL1: 2026全年 | AM1: 2027全年 | AN1: 2028全年
A2: 月份佔該季比重 | B2: 0.346019 | C2: 0.285433 | D2: 0.368548 | E2: 0.304683 | F2: 0.329835 | G2: 0.365481 | H2: 0.329563 | I2: 0.326718 | J2: 0.34372 | K2: 0.305382 | L2: 0.33508 | M2: 0.359538 | N2: 0.332244 | O2: 0.284843 | P2: 0.382912 | Q2: 0.313725 | R2: 0.334281 | S2: 0.351993 | T2: 0.319663 | U2: 0.334291 | V2: 0.346046 | W2: 0.321978 | X2: 0.332831 | Y2: 0.345191 | Z2: 0.333813 | AA2: 0.284646 | AB2: 0.381542 | AC2: 0.318993 | AD2: 0.335803 | AE2: 0.345203 | AF2: 0.328951 | AG2: 0.333792 | AH2: 0.337258 | AI2: 0.329814 | AJ2: 0.333388 | AK2: 0.336798
A3: 營收 | B3: =1_營收驅動!B19*B2 -> 31.636523 | C3: =1_營收驅動!B19*C2 -> 26.097144 | D3: =1_營收驅動!B19*D2 -> 33.696349 | E3: =1_營收驅動!C19*E2 -> 35.129952 | F3: =1_營收驅動!C19*F2 -> 38.029978 | G3: =1_營收驅動!C19*G2 -> 42.139962 | H3: =1_營收驅動!D19*H2 -> 47.49001 | I3: =1_營收驅動!D19*I2 -> 47.080046 | J3: =1_營收驅動!D19*J2 -> 49.530033 | K3: =1_營收驅動!E19*K2 -> 54.190052 | L3: =1_營收驅動!E19*L2 -> 59.459963 | M3: =1_營收驅動!E19*M2 -> 63.800037 | N3: =1_營收驅動!F19*N2 -> 68.143262 | O3: =1_營收驅動!F19*O2 -> 58.421315 | P3: =1_營收驅動!F19*P2 -> 78.535272 | Q3: =1_營收驅動!G19*Q2 -> 72.824972 | R3: =1_營收驅動!G19*R2 -> 77.596636 | S3: =1_營收驅動!G19*S2 -> 81.708122 | T3: =1_營收驅動!H19*T2 -> 84.576441 | U3: =1_營收驅動!H19*U2 -> 88.446717 | V3: =1_營收驅動!H19*V2 -> 91.556856 | W3: =1_營收驅動!I19*W2 -> 91.940835 | X3: =1_營收驅動!I19*X2 -> 95.03991 | Y3: =1_營收驅動!I19*Y2 -> 98.569309 | Z3: =1_營收驅動!J19*Z2 -> 95.340313 | AA3: =1_營收驅動!J19*AA2 -> 81.297729 | AB3: =1_營收驅動!J19*AB2 -> 108.97219 | AC3: =1_營收驅動!K19*AC2 -> 99.777828 | AD3: =1_營收驅動!K19*AD2 -> 105.03583 | AE3: =1_營收驅動!K19*AE2 -> 107.97606 | AF3: =1_營收驅動!L19*AF2 -> 112.96506 | AG3: =1_營收驅動!L19*AG2 -> 114.62751 | AH3: =1_營收驅動!L19*AH2 -> 115.81777 | AI3: =1_營收驅動!M19*AI2 -> 118.68684 | AJ3: =1_營收驅動!M19*AJ2 -> 119.97298 | AK3: =1_營收驅動!M19*AK2 -> 121.2001 | AL3: =SUM(B3:M3) -> 528.28005 | AM3: =SUM(N3:Y3) -> 987.35965 | AN3: =SUM(Z3:AK3) -> 1301.6702
A4: 營業毛利率 | B4: =1_營收驅動!B20 -> 0.1142 | C4: =1_營收驅動!B20 -> 0.1142 | D4: =1_營收驅動!B20 -> 0.1142 | E4: =1_營收驅動!C20 -> 0.2202 | F4: =1_營收驅動!C20 -> 0.2202 | G4: =1_營收驅動!C20 -> 0.2202 | H4: =1_營收驅動!D20 -> 0.29057329 | I4: =1_營收驅動!D20 -> 0.29057329 | J4: =1_營收驅動!D20 -> 0.29057329 | K4: =1_營收驅動!E20 -> 0.29970755 | L4: =1_營收驅動!E20 -> 0.29970755 | M4: =1_營收驅動!E20 -> 0.29970755 | N4: =1_營收驅動!F20 -> 0.31640059 | O4: =1_營收驅動!F20 -> 0.31640059 | P4: =1_營收驅動!F20 -> 0.31640059 | Q4: =1_營收驅動!G20 -> 0.33026503 | R4: =1_營收驅動!G20 -> 0.33026503 | S4: =1_營收驅動!G20 -> 0.33026503 | T4: =1_營收驅動!H20 -> 0.34241333 | U4: =1_營收驅動!H20 -> 0.34241333 | V4: =1_營收驅動!H20 -> 0.34241333 | W4: =1_營收驅動!I20 -> 0.35286249 | X4: =1_營收驅動!I20 -> 0.35286249 | Y4: =1_營收驅動!I20 -> 0.35286249 | Z4: =1_營收驅動!J20 -> 0.35819239 | AA4: =1_營收驅動!J20 -> 0.35819239 | AB4: =1_營收驅動!J20 -> 0.35819239 | AC4: =1_營收驅動!K20 -> 0.36233945 | AD4: =1_營收驅動!K20 -> 0.36233945 | AE4: =1_營收驅動!K20 -> 0.36233945 | AF4: =1_營收驅動!L20 -> 0.36706734 | AG4: =1_營收驅動!L20 -> 0.36706734 | AH4: =1_營收驅動!L20 -> 0.36706734 | AI4: =1_營收驅動!M20 -> 0.37087437 | AJ4: =1_營收驅動!M20 -> 0.37087437 | AK4: =1_營收驅動!M20 -> 0.37087437 | AL4: =AL5/AL3 -> 0.24775704 | AM4: =AM5/AM3 -> 0.33717569 | AN4: =AN5/AN3 -> 0.3650364
A5: 營業毛利 | B5: =B3*B4 -> 3.6128909 | C5: =C3*C4 -> 2.9802938 | D5: =D3*D4 -> 3.8481231 | E5: =E3*E4 -> 7.7356154 | F5: =F3*F4 -> 8.3742011 | G5: =G3*G4 -> 9.2792195 | H5: =H3*H4 -> 13.799328 | I5: =I3*I4 -> 13.680204 | ... AK5: =AK3*AK4 -> 44.950012 | AL5: =SUM(B5:M5) -> 130.8851 | AM5: =SUM(N5:Y5) -> 332.91367 | AN5: =SUM(Z5:AK5) -> 475.15701
A6: 營業費用率 | B6: 0.0678 | C6: 0.0678 | D6: 0.0678 | E6: 0.0599 | F6: 0.0599 | G6: 0.0599 | H6: 0.0555 | I6: 0.0555 | J6: 0.0555 | K6: 0.052 | L6: 0.052 | M6: 0.052 | N6: 0.056 | O6: 0.056 | P6: 0.056 | Q6: 0.056 | R6: 0.056 | S6: 0.056 | T6: 0.056 | U6: 0.056 | V6: 0.056 | W6: 0.056 | X6: 0.056 | Y6: 0.056 | Z6: 0.0587 | AA6: 0.0587 | AB6: 0.0587 | AC6: 0.0587 | AD6: 0.0587 | AE6: 0.0587 | AF6: 0.0587 | AG6: 0.0587 | AH6: 0.0587 | AI6: 0.0587 | AJ6: 0.0587 | AK6: 0.0587 | AL6: =AL7/AL3 -> 0.057413443 | AM6: =AM7/AM3 -> 0.056 | AN6: =AN7/AN3 -> 0.0587
A7: 營業費用（月） | B7: =B3*B6 -> 2.1449562 | C7: =C3*C6 -> 1.7693863 | D7: =D3*D6 -> 2.2846125 | E7: =E3*E6 -> 2.1042841 | F7: =F3*F6 -> 2.2779957 | G7: =G3*G6 -> 2.5241837 | H7: =H3*H6 -> 2.6356956 | I7: =I3*I6 -> 2.6129426 | ... AK7: =AK3*AK6 -> 7.1144461 | AL7: =SUM(B7:M7) -> 30.330376 | AM7: =SUM(N7:Y7) -> 55.29214 | AN7: =SUM(Z7:AK7) -> 76.408041
A8: 營業利益 | B8: =B5-B7 -> 1.4679347 | C8: =C5-C7 -> 1.2109075 | D8: =D5-D7 -> 1.5635106 | E8: =E5-E7 -> 5.6313313 | F8: =F5-F7 -> 6.0962054 | G8: =G5-G7 -> 6.7550358 | H8: =H5-H7 -> 11.163633 | I8: =I5-I7 -> 11.067261 | ... AK8: =AK5-AK7 -> 37.835565 | AL8: =SUM(B8:M8) -> 100.55472 | AM8: =SUM(N8:Y8) -> 277.62153 | AN8: =SUM(Z8:AK8) -> 398.74897
A9: 營業利益率 | B9: =B8/B3 -> 0.0464 | C9: =C8/C3 -> 0.0464 | D9: =D8/D3 -> 0.0464 | E9: =E8/E3 -> 0.1603 | F9: =F8/F3 -> 0.1603 | G9: =G8/G3 -> 0.1603 | H9: =H8/H3 -> 0.23507329 | I9: =I8/I3 -> 0.23507329 | ... AN9: =AN8/AN3 -> 0.3063364
A10: 業外收益 | B10: 0.2033 | C10: 0.2033 | D10: 0.2033 | E10: -0.0467 | F10: -0.0467 | G10: -0.0467 | H10: 0.1 | I10: 0.1 | J10: 0.1 | K10: 0.1 | L10: 0.1 | M10: 0.1 | N10: 0.1 | O10: 0.1 | P10: 0.1 | Q10: 0.1 | R10: 0.1 | S10: 0.1 | T10: 0.1 | U10: 0.1 | V10: 0.1 | W10: 0.1 | X10: 0.1 | Y10: 0.1 | Z10: 0.1 | AA10: 0.1 | AB10: 0.1 | AC10: 0.1 | AD10: 0.1 | AE10: 0.1 | AF10: 0.1 | AG10: 0.1 | AH10: 0.1 | AI10: 0.1 | AJ10: 0.1 | AK10: 0.1 | AL10: =SUM(B10:M10) -> 1.0698 | AM10: =SUM(N10:Y10) -> 1.2 | AN10: =SUM(Z10:AK10) -> 1.2
A11: 稅前淨利 | B11: =B8+B10 -> 1.6712347 | C11: =C8+C10 -> 1.4142075 | D11: =D8+D10 -> 1.7668106 | E11: =E8+E10 -> 5.5846313 | F11: =F8+F10 -> 6.0495054 | G11: =G8+G10 -> 6.7083358 | H11: =H8+H10 -> 11.263633 | I11: =I8+I10 -> 11.167261 | ... AK11: =AK8+AK10 -> 37.935565 | AL11: =SUM(B11:M11) -> 101.62452 | AM11: =SUM(N11:Y11) -> 278.82153 | AN11: =SUM(Z11:AK11) -> 399.94897
A12: 稅前淨利率 | B12: =B11/B3 -> 0.052826117 | C12: =C11/C3 -> 0.054190125 | D12: =D11/D3 -> 0.052433295 | E12: =E11/E3 -> 0.15897065 | F12: =F11/F3 -> 0.15907202 | G12: =G11/G3 -> 0.15919179 | H12: =H11/H3 -> 0.23717899 | I12: =I11/I3 -> 0.23719733 | ... AN12: =AN11/AN3 -> 0.30725829
A13: 有效稅率 | B13: 0.348 | C13: 0.348 | D13: 0.348 | E13: 0.3024 | F13: 0.3024 | G13: 0.3024 | H13: 0.3 | I13: 0.3 | J13: 0.3 | K13: 0.3 | L13: 0.3 | M13: 0.3 | N13: 0.275 | O13: 0.275 | P13: 0.275 | Q13: 0.275 | R13: 0.275 | S13: 0.275 | T13: 0.275 | U13: 0.275 | V13: 0.275 | W13: 0.275 | X13: 0.275 | Y13: 0.275 | Z13: 0.275 | AA13: 0.275 | AB13: 0.275 | AC13: 0.275 | AD13: 0.275 | AE13: 0.275 | AF13: 0.275 | AG13: 0.275 | AH13: 0.275 | AI13: 0.275 | AJ13: 0.275 | AK13: 0.275 | AL13: =AL14/AL11 -> 0.30272503 | AM13: =AM14/AM11 -> 0.275 | AN13: =AN14/AN11 -> 0.275
A14: 所得稅費用 | B14: =B11*B13 -> 0.58158966 | C14: =C11*C13 -> 0.4921442 | D14: =D11*D13 -> 0.61485009 | E14: =E11*E13 -> 1.6887925 | F14: =F11*F13 -> 1.8293704 | G14: =G11*G13 -> 2.0286008 | H14: =H11*H13 -> 3.3790899 | I14: =I11*I13 -> 3.3501784 | ... AK14: =AK11*AK13 -> 10.432281 | AL14: =SUM(B14:M14) -> 30.764288 | AM14: =SUM(N14:Y14) -> 76.675922 | AN14: =SUM(Z14:AK14) -> 109.98597
A15: 稅後淨利 | B15: =B11-B14 -> 1.089645 | C15: =C11-C14 -> 0.92206327 | D15: =D11-D14 -> 1.1519605 | E15: =E11-E14 -> 3.8958388 | F15: =F11-F14 -> 4.220135 | G15: =G11-G14 -> 4.6797351 | H15: =H11-H14 -> 7.884543 | I15: =I11-I14 -> 7.8170829 | ... AK15: =AK11-AK14 -> 27.503285 | AL15: =SUM(B15:M15) -> 70.860237 | AM15: =SUM(N15:Y15) -> 202.14561 | AN15: =SUM(Z15:AK15) -> 289.963
A16: 稅後淨利率 | B16: =B15/B3 -> 0.034442628 | C16: =C15/C3 -> 0.035331961 | D16: =D15/D3 -> 0.034186508 | E16: =E15/E3 -> 0.11089793 | F16: =F15/F3 -> 0.11096864 | G16: =G15/G3 -> 0.11105219 | H16: =H15/H3 -> 0.1660253 | I16: =I15/I3 -> 0.16603813 | ... AN16: =AN15/AN3 -> 0.22276226
A17: 稅後淨利（歸母） | B17: =B15 -> 1.089645 | C17: =C15 -> 0.92206327 | D17: =D15 -> 1.1519605 | E17: =E15 -> 3.8958388 | F17: =F15 -> 4.220135 | G17: =G15 -> 4.6797351 | H17: =H15 -> 7.884543 | I17: =I15 -> 7.8170829 | ... AK17: =AK15 -> 27.503285 | AL17: =SUM(B17:M17) -> 70.860237 | AM17: =SUM(N17:Y17) -> 202.14561 | AN17: =SUM(Z17:AK17) -> 289.963
A18: 股數（億股） | B18: 3.635 | C18: 3.635 | D18: 3.635 | E18: 3.635 | F18: 3.635 | G18: 3.635 | H18: 3.635 | I18: 3.635 | J18: 3.635 | K18: 3.635 | L18: 3.635 | M18: 3.635 | N18: 3.635 | O18: 3.635 | P18: 3.635 | Q18: 3.635 | R18: 3.635 | S18: 3.635 | T18: 3.635 | U18: 3.635 | V18: 3.635 | W18: 3.635 | X18: 3.635 | Y18: 3.635 | Z18: 3.635 | AA18: 3.635 | AB18: 3.635 | AC18: 3.635 | AD18: 3.635 | AE18: 3.635 | AF18: 3.635 | AG18: 3.635 | AH18: 3.635 | AI18: 3.635 | AJ18: 3.635 | AK18: 3.635 | AL18: 3.635 | AM18: 3.635 | AN18: 3.635
A19: EPS（元） | B19: =B17/B18 -> 0.29976478 | C19: =C17/C18 -> 0.25366252 | D19: =D17/D18 -> 0.31690798 | E19: =E17/E18 -> 1.0717576 | F19: =F17/F18 -> 1.1609725 | G19: =G17/G18 -> 1.2874099 | H19: =H17/H18 -> 2.1690627 | I19: =I17/I18 -> 2.1505042 | ... AN19: =AN17/AN18 -> 79.769739
A20: EPS 每季 | B20: =SUM(B19:D19) -> 0.87033529 | E20: =SUM(E19:G19) -> 3.52014 | H20: =SUM(H19:J19) -> 6.5809786 | K20: =SUM(K19:M19) -> 8.5224215 | N20: =SUM(N19:P19) -> 10.712074 | Q20: =SUM(Q19:S19) -> 12.75782 | T20: =SUM(T19:V19) -> 15.17399 | W20: =SUM(W19:Y19) -> 16.967015 | Z20: =SUM(Z19:AB19) -> 17.12039 | AC20: =SUM(AC19:AE19) -> 19.002638 | AF20: =SUM(AF19:AH19) -> 21.180877 | AI20: =SUM(AI19:AK19) -> 22.465834
A22: 年 EPS | AL22: =AL19 -> 19.493875 | AM22: =AM19 -> 55.610898 | AN22: =AN19 -> 79.769739

Sheet 3_彙總與對照
A1: v31 vs v30 vs 外部預估
A3: 項目 | B3: 2026 | C3: 2027 | D3: 2028
A4: v31 營收（億） | B4: =2_月度損益表!AL3 -> 528.28005 | C4: =2_月度損益表!AM3 -> 987.35965 | D4: =2_月度損益表!AN3 -> 1301.6702
A5: v31 毛利率 | B5: =2_月度損益表!AL4 -> 0.24775704 | C5: =2_月度損益表!AM4 -> 0.33717569 | D5: =2_月度損益表!AN4 -> 0.3650364
A6: v31 稅前淨利（億） | B6: =2_月度損益表!AL11 -> 101.62452 | C6: =2_月度損益表!AM11 -> 278.82153 | D6: =2_月度損益表!AN11 -> 399.94897
A7: v31 稅後淨利（億） | B7: =2_月度損益表!AL17 -> 70.860237 | C7: =2_月度損益表!AM17 -> 202.14561 | D7: =2_月度損益表!AN17 -> 289.963
A8: v31 EPS（元） | B8: =2_月度損益表!AL19 -> 19.493875 | C8: =2_月度損益表!AM19 -> 55.610898 | D8: =2_月度損益表!AN19 -> 79.769739
A10: 對照（EPS，元）
A11: v30（20260818） | B11: 19.38 | C11: 52.22 | D11: 71.37
A12: v29（20260817） | B12: 19.11 | C12: 50.42 | D12: 74.53
A13: memo 內部模型（20260814） | B13: 19.5 | C13: 39.67 | D13: —
A14: 法人共識（20260813） | B14: 12.82 | C14: 22.69 | D14: 14.8
A15: 凱基投顧（20260807） | B15: 12.77 | C15: 20.34 | D15: —
A17: v31 − v30（元） | B17: =B8-B11 -> 0.11387546 | C17: =C8-C11 -> 3.3908975 | D17: =D8-D11 -> 8.3997387
A19: 現價 488 元（2026/08/18 收）隱含 PE | B19: =488/2_月度損益表!AL19 -> 25.033504 | C19: =488/2_月度損益表!AM19 -> 8.7752585 | D19: =488/2_月度損益表!AN19 -> 6.1176081
