Workbook

Sheet 0_變量總覽
A1: 估值變量確認總覽 — 台燿（6274）
A2: 報告日期：20260710｜本表為唯讀摘要，實際輸入請至「1_輸入區」修改
A4: 變量 | B4: 採用值 | C4: 來源 | D4: 影響方向
A5: 現價 | B5: 1570.0 元 | C5: Yahoo股市 2026/07/09收盤1570.0元 +4.56%，本益比113.44x（同業平均111.25x），Claude in Chrome抓取 | D5: 估值基準
A6: 基期EPS | B6: 12.13 元（2025） | C6: 2025全年EPS 12.13元，來源Yahoo股市/uanalyze年度共識一致 | D6: 估值基準
A7: ELL+SLL 超低損耗材料（對應800G交換器/AI ASIC） 成長率 | B7: 135% / 100% / 65% | C7: 26Q1法說會揭露產品結構ELL+SLL佔營收38%（來源aistockmap.com AI智慧產業地圖，2026-07-10抓取）；以此比例反推2025全年營收303.4億元之ELL+SLL分項=303.4×38%=115.29億（推估，2025年報未逐產品線揭露，假設26Q1結構近似全年結構）；2026-2028成長率設為135%/100%/65%，反映高階材料佔比持續提升敘事（ELL+SLL佔總營收比重由38%→45.3%→51.1%→54.3%），使四線加總營收貼近法人共識(599.35/1048.29/1611.84億元，模型加總誤差-0.3%/+1.2%/+2.2%，均在±5%容許範圍內) | D7: 營收→EPS
A8: VLL+LL 低損耗材料 成長率 | B8: 90% / 65% / 50% | C8: 同上圖反推VLL+LL佔比32%，2025全年=303.4×32%=97.09億(推估，同上假設)；2026-2028成長率90%/65%/50%，次於ELL+SLL但仍受惠整體高速傳輸材料需求 | D8: 營收→EPS
A9: HDI+N-LL 成長率 | B9: 60% / 55% / 40% | C9: 同上圖反推HDI+N-LL佔比18%，2025全年=303.4×18%=54.61億(推估，同上假設)；2026-2028成長率60%/55%/40%，成熟產品線成長動能較低階材料放緩 | D9: 營收→EPS
A10: 其他 成長率 | B10: 50% / 45% / 35% | C10: 同上圖反推其他佔比12%，2025全年=303.4×12%=36.41億(推估，同上假設)；2026-2028成長率50%/45%/35%，隨整體需求成長但佔比逐年稀釋 | D10: 營收→EPS
A11: 毛利率路徑 | B11: 29.0% / 32.0% / 35.0% | C11: 26Q1法說會實際毛利率25.15%為起點；為貼近法人共識EPS陡峭成長軌跡(YoY+117%/+69%/+69%)，模型毛利率路徑設定29%/32%/35%（隨ELL+SLL高毛利產品線佔比由38%快速提升至54.3%，帶動整體毛利率結構性上升，此為合理但尚未經公司逐產品線利潤率證實之推估）；此路徑高於Wallace原先「基本情境毛利率25-27%」的敘事假設，兩者存在張力——若僅維持25-27%毛利率，反推所需營業費用率將趨近於0%（不合理），故改以毛利率上修來吸收法人共識隱含的營運槓桿效果，詳見0_變量總覽分頁「模型EPS vs法人共識誤差」列說明；未超過40%上限 | D11: EPS
A12: 目標PE區間 | B12: 45.0x - 50.0x | C12: 基本情境目標PE 45-50x，相對法人共識2027F EPS 76.4元計算之forward PE，反映部分本益比壓縮但仍認可高成長；現況台燿/台光電(2383)/聯茂(6213)三檔CCL廠trailing PE分別113.44x/114.86x/94.13x(2026/07/09收盤，Chrome抓取)，全產業均在94-115x高檔 | D12: 目標價
A13: 現況PE基準 | B13: 113.44x | C13: Yahoo股市2026/07/09收盤：1570.0元，本益比113.44x（同業平均111.25x），Claude in Chrome抓取 | D13: 對照組
A14: 產業平均成長率 | B14: 19% | C14: 產業（CCL/高階材料）近期成長動能強勁但無精確產業平均數字，推估18%-20%取中19%，缺乏TrendForce/Gartner等第三方數字 | D14: 隱含成長率檢核
A15: 法人共識EPS來源確認（爭議澄清） | B15: 採35.27/76.4/128.95元（2026-2028F） | C15: 估值變量確認關卡過程中曾出現兩組法人共識矛盾數字(18.22元 vs 35.27元)；經Wallace親自截圖優分析uanalyze網站圖表確認，2026F EPS採35.27元一組為準(法人平均預估)，本模型全數以此組數字為錨點 | D15: 估值基準/風險揭露
... A18: 紅隊技術面風險 | B18: 週RSI頂背離／KD死叉／MACD收斂／OBV走弱，正上方1598-1694元套牢帶 | C18: 為保守情境目標PE壓至25-30x(戴維斯雙殺)之主要理由 | D18: 保守情境PE依據

Sheet 1_輸入區
A1: 估值輸入區 — 台燿（6274）
A2: 報告日期 20260710｜藍字黃底＝可自行改動，改動後全表即時重算
A4: ① 基本資料
A5: 現價（元） | B5: 1570 | C5: 來源：Yahoo股市 2026/07/09收盤1570.0元 +4.56%，本益比113.44x（同業平均111.25x），Claude in Chrome抓取
A6: 在外流通股數（億股） | B6: 2.8877464 | C6: 來源：已發行普通股數288,774,637股，來源Yahoo股市基本資料2026/07/10
A7: 基期年度 | B7: 2025
A8: 基期 EPS（元） | B8: 12.13 | C8: 來源：2025全年EPS 12.13元，來源Yahoo股市/uanalyze年度共識一致
A10: ② 營收假設（億元）
A11: 產品線 | B11: 2025基期營收 | C11: 2026 成長率 | D11: 2027 成長率 | E11: 2028 成長率 | F11: 來源備註
A12: ELL+SLL 超低損耗材料（對應800G交換器/AI ASIC） | B12: 115.29 | C12: 1.35 | D12: 1 | E12: 0.65 | F12: 來源：26Q1法說會揭露產品結構ELL+SLL佔營收38%（來源aistockmap.com AI智慧產業地圖，2026-07-10抓取）；以此比例反推2025全年營收303.4億元之ELL+SLL分項=303.4×38%=115.29億（推估，2025年報未逐產品線揭露，假設26Q1結構近似全年結構）；2026-2028成長率設為135%/100%/65%，反映高階材料佔比持續提升敘事（ELL+SLL佔總營收比重由38%→45.3%→51.1%→54.3%），使四線加總營收貼近法人共識(599.35/1048.29/1611.84億元，模型加總誤差-0.3%/+1.2%/+2.2%，均在±5%容許範圍內)
A13: VLL+LL 低損耗材料 | B13: 97.09 | C13: 0.9 | D13: 0.65 | E13: 0.5 | F13: 來源：同上圖反推VLL+LL佔比32%，2025全年=303.4×32%=97.09億(推估，同上假設)；2026-2028成長率90%/65%/50%，次於ELL+SLL但仍受惠整體高速傳輸材料需求
A14: HDI+N-LL | B14: 54.61 | C14: 0.6 | D14: 0.55 | E14: 0.4 | F14: 來源：同上圖反推HDI+N-LL佔比18%，2025全年=303.4×18%=54.61億(推估，同上假設)；2026-2028成長率60%/55%/40%，成熟產品線成長動能較低階材料放緩
A15: 其他 | B15: 36.41 | C15: 0.5 | D15: 0.45 | E15: 0.35 | F15: 來源：同上圖反推其他佔比12%，2025全年=303.4×12%=36.41億(推估，同上假設)；2026-2028成長率50%/45%/35%，隨整體需求成長但佔比逐年稀釋
A17: ③ 利潤率假設
A18: 項目 | B18: 2026 | C18: 2027 | D18: 2028 | E18: 來源備註
A19: 毛利率 | B19: 0.29 | C19: 0.32 | D19: 0.35 | E19: 來源：26Q1法說會實際毛利率25.15%為起點；為貼近法人共識EPS陡峭成長軌跡(YoY+117%/+69%/+69%)，模型毛利率路徑設定29%/32%/35%（隨ELL+SLL高毛利產品線佔比由38%快速提升至54.3%，帶動整體毛利率結構性上升，此為合理但尚未經公司逐產品線利潤率證實之推估）；此路徑高於Wallace原先「基本情境毛利率25-27%」的敘事假設，兩者存在張力——若僅維持25-27%毛利率，反推所需營業費用率將趨近於0%（不合理），故改以毛利率上修來吸收法人共識隱含的營運槓桿效果，詳見0_變量總覽分頁「模型EPS vs法人共識誤差」列說明；未超過40%上限
A20: 營業費用率 | B20: 0.08 | C20: 0.075 | D20: 0.07 | E20: 來源：推估：隨營收規模擴大（303.4億→1611.84億）產生費用攤薄效果，費用率由8.0%緩步降至7.0%，屬中性假設（無公司逐年費用率指引可比對，標「推估」）
A21: 業外收支/營收 | B21: -0.003 | C21: -0.003 | D21: -0.003 | E21: 來源：推估：反映紅隊指出之負債比14個月由40%攀升至59.2%，利息費用轉為業外淨支出，估-0.3%（無精確業外收支預估數字，標「推估」）
A22: 有效稅率 | B22: 0.2 | C22: 0.2 | D22: 0.2 | E22: 來源：採台灣一般營利事業所得稅率20%（推估，無公司揭露之有效稅率可比對）
A24: ④ 估值假設
A25: 目標 PE 下緣 | B25: 45 | C25: 來源：基本情境目標PE 45-50x，相對法人共識2027F EPS 76.4元計算之forward PE，反映部分本益比壓縮但仍認可高成長；現況台燿/台光電(2383)/聯茂(6213)三檔CCL廠trailing PE分別113.44x/114.86x/94.13x(2026/07/09收盤，Chrome抓取)，全產業均在94-115x高檔
A26: 目標 PE 上緣 | B26: 50
A27: 出場 PE（隱含成長率檢核） | B27: 47.5
A28: 評估年數 N | B28: 1.5
A29: 產業平均 EPS 成長率 | B29: 0.19 | C29: 來源：產業（CCL/高階材料）近期成長動能強勁但無精確產業平均數字，推估18%-20%取中19%，缺乏TrendForce/Gartner等第三方數字
A30: 現況本益比基準（不含重評，對照用） | B30: 113.44 | C30: 來源：Yahoo股市2026/07/09收盤：1570.0元，本益比113.44x（同業平均111.25x），Claude in Chrome抓取
A32: ⑤ 情境調整（相對基本假設）
A33: 情境 | B33: 機率 | C33: 營收成長率調整 | D33: 毛利率調整 | E33: 情境 PE | F33: 情境說明
A34: 樂觀 | B34: 0.25 | C34: 0.2 | D34: 0.03 | E34: 65 | F34: product line成長優於法人共識(尤其ELL/SLL佔比超預期提升)，毛利率上看28%+(對應本模型基本情境已上修後之路徑再加碼)，目標PE 60-70x取中65x，維持接近現況同業水準
A35: 基本 | B35: 0.45 | C35: 0 | D35: 0 | E35: 47.5 | F35: 完全對齊法人共識(2026 EPS 35.27／2027 EPS 76.4／2028 EPS 128.95)，目標PE 45-50x取中47.5x
A36: 保守 | B36: 0.3 | C36: -0.65 | D36: -0.125 | E36: 27.5 | F36: 紅隊三大論證情境(EPS成長不如共識、FCF/負債體質未改善、技術面隨頂背離修正拖累估值)：營收成長打6-7折於法人共識隱含成長率、毛利率回落至22-23%，雙重下修使EPS較基本情境約再腰斬(-65%)，目標PE壓至25-30x取中27.5x(戴維斯雙殺)

Sheet 2_EPS計算
A1: EPS 計算（全公式，勿直接改本表——請改 1_輸入區）
A3: 項目 | B3: 2025A | C3: 2026E | D3: 2027E | E3: 2028E
A4: ELL+SLL 超低損耗材料（對應800G交換器/AI ASIC） 營收 | B4: ='1_輸入區'!B12 -> 115.29 | C4: =B4*(1+'1_輸入區'!C12) -> 270.9315 | D4: =C4*(1+'1_輸入區'!D12) -> 541.863 | E4: =D4*(1+'1_輸入區'!E12) -> 894.07395
A5: VLL+LL 低損耗材料 營收 | B5: ='1_輸入區'!B13 -> 97.09 | C5: =B5*(1+'1_輸入區'!C13) -> 184.471 | D5: =C5*(1+'1_輸入區'!D13) -> 304.37715 | E5: =D5*(1+'1_輸入區'!E13) -> 456.56572
A6: HDI+N-LL 營收 | B6: ='1_輸入區'!B14 -> 54.61 | C6: =B6*(1+'1_輸入區'!C14) -> 87.376 | D6: =C6*(1+'1_輸入區'!D14) -> 135.4328 | E6: =D6*(1+'1_輸入區'!E14) -> 189.60592
A7: 其他 營收 | B7: ='1_輸入區'!B15 -> 36.41 | C7: =B7*(1+'1_輸入區'!C15) -> 54.615 | D7: =C7*(1+'1_輸入區'!D15) -> 79.19175 | E7: =D7*(1+'1_輸入區'!E15) -> 106.90886
A8: 總營收（億元） | B8: =SUM(B4:B7) -> 303.4 | C8: =SUM(C4:C7) -> 597.3935 | D8: =SUM(D4:D7) -> 1060.8647 | E8: =SUM(E4:E7) -> 1647.1545
A9: 毛利率 | B9: n/a | C9: ='1_輸入區'!B19 -> 0.29 | D9: ='1_輸入區'!C19 -> 0.32 | E9: ='1_輸入區'!D19 -> 0.35
A10: 營業毛利（億元） | B10: n/a | C10: =C8*C9 -> 173.24411 | D10: =D8*D9 -> 339.4767 | E10: =E8*E9 -> 576.50406
A11: 營業費用率 | B11: n/a | C11: ='1_輸入區'!B20 -> 0.08 | D11: ='1_輸入區'!C20 -> 0.075 | E11: ='1_輸入區'!D20 -> 0.07
A12: 營業利益（億元） | B12: n/a | C12: =C10-C8*C11 -> 125.45264 | D12: =D10-D8*D11 -> 259.91185 | E12: =E10-E8*E11 -> 461.20325
A13: 業外收支率 | B13: n/a | C13: ='1_輸入區'!B21 -> -0.003 | D13: ='1_輸入區'!C21 -> -0.003 | E13: ='1_輸入區'!D21 -> -0.003
A14: 稅前淨利（億元） | B14: n/a | C14: =C12+C8*C13 -> 123.66045 | D14: =D12+D8*D13 -> 256.72926 | E14: =E12+E8*E13 -> 456.26178
A15: 有效稅率 | B15: n/a | C15: ='1_輸入區'!B22 -> 0.2 | D15: ='1_輸入區'!C22 -> 0.2 | E15: ='1_輸入區'!D22 -> 0.2
A16: 稅後淨利（億元） | B16: n/a | C16: =C14*(1-C15) -> 98.928364 | D16: =D14*(1-D15) -> 205.38341 | E16: =E14*(1-E15) -> 365.00943
A17: EPS（元） | B17: ='1_輸入區'!$B$8 -> 12.13 | C17: =C16/'1_輸入區'!$B$6 -> 34.257982 | D17: =D16/'1_輸入區'!$B$6 -> 71.122384 | E17: =E16/'1_輸入區'!$B$6 -> 126.39941
A19: 目標價（PE下緣） | C19: =C17*'1_輸入區'!$B$25 -> 1541.6092 | D19: =D17*'1_輸入區'!$B$25 -> 3200.5073 | E19: =E17*'1_輸入區'!$B$25 -> 5687.9733
A20: 目標價（PE上緣） | C20: =C17*'1_輸入區'!$B$26 -> 1712.8991 | D20: =D17*'1_輸入區'!$B$26 -> 3556.1192 | E20: =E17*'1_輸入區'!$B$26 -> 6319.9703

Sheet 3_敏感度
A1: 敏感度矩陣（以最後預測年度為基準）
A3: 矩陣A：2028E 總營收YoY × 毛利率 → EPS
A5: 營收YoY\毛利率 | B5: ='1_輸入區'!D19+-0.05 -> 0.3 | C5: ='1_輸入區'!D19+-0.03 -> 0.32 | D5: ='1_輸入區'!D19+-0.015 -> 0.335 | E5: ='1_輸入區'!D19+0 -> 0.35 | F5: ='1_輸入區'!D19+0.015 -> 0.365 | G5: ='1_輸入區'!D19+0.03 -> 0.38 | H5: ='1_輸入區'!D19+0.05 -> 0.4
A6: =SUMPRODUCT('1_輸入區'!B12:B15,'1_輸入區'!E12:E15)/SUM('1_輸入區'!B12:B15)+-0.15 -> 0.37099868 | B6: =('2_EPS計算'!E8*(1+-0.15)*(('1_輸入區'!D19+-0.05)-'1_輸入區'!D20)*(1+'1_輸入區'!D21)*(1-'1_輸入區'!D22))/'1_輸入區'!$B$6 -> 88.94206 | C6: =('2_EPS計算'!E8*(1+-0.15)*(('1_輸入區'!D19+-0.03)-'1_輸入區'!D20)*(1+'1_輸入區'!D21)*(1-'1_輸入區'!D22))/'1_輸入區'!$B$6 -> 96.676153 | D6: =('2_EPS計算'!E8*(1+-0.15)*(('1_輸入區'!D19+-0.015)-'1_輸入區'!D20)*(1+'1_輸入區'!D21)*(1-'1_輸入區'!D22))/'1_輸入區'!$B$6 -> 102.47672 | E6: =('2_EPS計算'!E8*(1+-0.15)*(('1_輸入區'!D19+0)-'1_輸入區'!D20)*(1+'1_輸入區'!D21)*(1-'1_輸入區'!D22))/'1_輸入區'!$B$6 -> 108.27729 | F6: =('2_EPS計算'!E8*(1+-0.15)*(('1_輸入區'!D19+0.015)-'1_輸入區'!D20)*(1+'1_輸入區'!D21)*(1-'1_輸入區'!D22))/'1_輸入區'!$B$6 -> 114.07786 | G6: =('2_EPS計算'!E8*(1+-0.15)*(('1_輸入區'!D19+0.03)-'1_輸入區'!D20)*(1+'1_輸入區'!D21)*(1-'1_輸入區'!D22))/'1_輸入區'!$B$6 -> 119.87843 | H6: =('2_EPS計算'!E8*(1+-0.15)*(('1_輸入區'!D19+0.05)-'1_輸入區'!D20)*(1+'1_輸入區'!D21)*(1-'1_輸入區'!D22))/'1_輸入區'!$B$6 -> 127.61252
A7: =SUMPRODUCT('1_輸入區'!B12:B15,'1_輸入區'!E12:E15)/SUM('1_輸入區'!B12:B15)+-0.1 -> 0.42099868 | B7: =('2_EPS計算'!E8*(1+-0.1)*(('1_輸入區'!D19+-0.05)-'1_輸入區'!D20)*(1+'1_輸入區'!D21)*(1-'1_輸入區'!D22))/'1_輸入區'!$B$6 -> 94.173946 | C7: =('2_EPS計算'!E8*(1+-0.1)*(('1_輸入區'!D19+-0.03)-'1_輸入區'!D20)*(1+'1_輸入區'!D21)*(1-'1_輸入區'!D22))/'1_輸入區'!$B$6 -> 102.36299 | D7: =('2_EPS計算'!E8*(1+-0.1)*(('1_輸入區'!D19+-0.015)-'1_輸入區'!D20)*(1+'1_輸入區'!D21)*(1-'1_輸入區'!D22))/'1_輸入區'!$B$6 -> 108.50476 | E7: =('2_EPS計算'!E8*(1+-0.1)*(('1_輸入區'!D19+0)-'1_輸入區'!D20)*(1+'1_輸入區'!D21)*(1-'1_輸入區'!D22))/'1_輸入區'!$B$6 -> 114.64654 | F7: =('2_EPS計算'!E8*(1+-0.1)*(('1_輸入區'!D19+0.015)-'1_輸入區'!D20)*(1+'1_輸入區'!D21)*(1-'1_輸入區'!D22))/'1_輸入區'!$B$6 -> 120.78832 | G7: =('2_EPS計算'!E8*(1+-0.1)*(('1_輸入區'!D19+0.03)-'1_輸入區'!D20)*(1+'1_輸入區'!D21)*(1-'1_輸入區'!D22))/'1_輸入區'!$B$6 -> 126.9301 | H7: =('2_EPS計算'!E8*(1+-0.1)*(('1_輸入區'!D19+0.05)-'1_輸入區'!D20)*(1+'1_輸入區'!D21)*(1-'1_輸入區'!D22))/'1_輸入區'!$B$6 -> 135.11914
A8: =SUMPRODUCT('1_輸入區'!B12:B15,'1_輸入區'!E12:E15)/SUM('1_輸入區'!B12:B15)+-0.05 -> 0.47099868 | B8: =('2_EPS計算'!E8*(1+-0.05)*(('1_輸入區'!D19+-0.05)-'1_輸入區'!D20)*(1+'1_輸入區'!D21)*(1-'1_輸入區'!D22))/'1_輸入區'!$B$6 -> 99.405832 | C8: =('2_EPS計算'!E8*(1+-0.05)*(('1_輸入區'!D19+-0.03)-'1_輸入區'!D20)*(1+'1_輸入區'!D21)*(1-'1_輸入區'!D22))/'1_輸入區'!$B$6 -> 108.04982 | D8: =('2_EPS計算'!E8*(1+-0.05)*(('1_輸入區'!D19+-0.015)-'1_輸入區'!D20)*(1+'1_輸入區'!D21)*(1-'1_輸入區'!D22))/'1_輸入區'!$B$6 -> 114.53281 | E8: =('2_EPS計算'!E8*(1+-0.05)*(('1_輸入區'!D19+0)-'1_輸入區'!D20)*(1+'1_輸入區'!D21)*(1-'1_輸入區'!D22))/'1_輸入區'!$B$6 -> 121.0158 | F8: =('2_EPS計算'!E8*(1+-0.05)*(('1_輸入區'!D19+0.015)-'1_輸入區'!D20)*(1+'1_輸入區'!D21)*(1-'1_輸入區'!D22))/'1_輸入區'!$B$6 -> 127.49878 | G8: =('2_EPS計算'!E8*(1+-0.05)*(('1_輸入區'!D19+0.03)-'1_輸入區'!D20)*(1+'1_輸入區'!D21)*(1-'1_輸入區'!D22))/'1_輸入區'!$B$6 -> 133.98177 | H8: =('2_EPS計算'!E8*(1+-0.05)*(('1_輸入區'!D19+0.05)-'1_輸入區'!D20)*(1+'1_輸入區'!D21)*(1-'1_輸入區'!D22))/'1_輸入區'!$B$6 -> 142.62576
A9: =SUMPRODUCT('1_輸入區'!B12:B15,'1_輸入區'!E12:E15)/SUM('1_輸入區'!B12:B15)+0 -> 0.52099868 | B9: =('2_EPS計算'!E8*(1+0)*(('1_輸入區'!D19+-0.05)-'1_輸入區'!D20)*(1+'1_輸入區'!D21)*(1-'1_輸入區'!D22))/'1_輸入區'!$B$6 -> 104.63772 | C9: =('2_EPS計算'!E8*(1+0)*(('1_輸入區'!D19+-0.03)-'1_輸入區'!D20)*(1+'1_輸入區'!D21)*(1-'1_輸入區'!D22))/'1_輸入區'!$B$6 -> 113.73665 | D9: =('2_EPS計算'!E8*(1+0)*(('1_輸入區'!D19+-0.015)-'1_輸入區'!D20)*(1+'1_輸入區'!D21)*(1-'1_輸入區'!D22))/'1_輸入區'!$B$6 -> 120.56085 | E9: =('2_EPS計算'!E8*(1+0)*(('1_輸入區'!D19+0)-'1_輸入區'!D20)*(1+'1_輸入區'!D21)*(1-'1_輸入區'!D22))/'1_輸入區'!$B$6 -> 127.38505 | F9: =('2_EPS計算'!E8*(1+0)*(('1_輸入區'!D19+0.015)-'1_輸入區'!D20)*(1+'1_輸入區'!D21)*(1-'1_輸入區'!D22))/'1_輸入區'!$B$6 -> 134.20925 | G9: =('2_EPS計算'!E8*(1+0)*(('1_輸入區'!D19+0.03)-'1_輸入區'!D20)*(1+'1_輸入區'!D21)*(1-'1_輸入區'!D22))/'1_輸入區'!$B$6 -> 141.03345 | H9: =('2_EPS計算'!E8*(1+0)*(('1_輸入區'!D19+0.05)-'1_輸入區'!D20)*(1+'1_輸入區'!D21)*(1-'1_輸入區'!D22))/'1_輸入區'!$B$6 -> 150.13238
A10: =SUMPRODUCT('1_輸入區'!B12:B15,'1_輸入區'!E12:E15)/SUM('1_輸入區'!B12:B15)+0.05 -> 0.57099868 | B10: =('2_EPS計算'!E8*(1+0.05)*(('1_輸入區'!D19+-0.05)-'1_輸入區'!D20)*(1+'1_輸入區'!D21)*(1-'1_輸入區'!D22))/'1_輸入區'!$B$6 -> 109.8696 | C10: =('2_EPS計算'!E8*(1+0.05)*(('1_輸入區'!D19+-0.03)-'1_輸入區'!D20)*(1+'1_輸入區'!D21)*(1-'1_輸入區'!D22))/'1_輸入區'!$B$6 -> 119.42348 | D10: =('2_EPS計算'!E8*(1+0.05)*(('1_輸入區'!D19+-0.015)-'1_輸入區'!D20)*(1+'1_輸入區'!D21)*(1-'1_輸入區'!D22))/'1_輸入區'!$B$6 -> 126.58889 | E10: =('2_EPS計算'!E8*(1+0.05)*(('1_輸入區'!D19+0)-'1_輸入區'!D20)*(1+'1_輸入區'!D21)*(1-'1_輸入區'!D22))/'1_輸入區'!$B$6 -> 133.7543 | F10: =('2_EPS計算'!E8*(1+0.05)*(('1_輸入區'!D19+0.015)-'1_輸入區'!D20)*(1+'1_輸入區'!D21)*(1-'1_輸入區'!D22))/'1_輸入區'!$B$6 -> 140.91971 | G10: =('2_EPS計算'!E8*(1+0.05)*(('1_輸入區'!D19+0.03)-'1_輸入區'!D20)*(1+'1_輸入區'!D21)*(1-'1_輸入區'!D22))/'1_輸入區'!$B$6 -> 148.08512 | H10: =('2_EPS計算'!E8*(1+0.05)*(('1_輸入區'!D19+0.05)-'1_輸入區'!D20)*(1+'1_輸入區'!D21)*(1-'1_輸入區'!D22))/'1_輸入區'!$B$6 -> 157.639
A11: =SUMPRODUCT('1_輸入區'!B12:B15,'1_輸入區'!E12:E15)/SUM('1_輸入區'!B12:B15)+0.1 -> 0.62099868 | B11: =('2_EPS計算'!E8*(1+0.1)*(('1_輸入區'!D19+-0.05)-'1_輸入區'!D20)*(1+'1_輸入區'!D21)*(1-'1_輸入區'!D22))/'1_輸入區'!$B$6 -> 115.10149 | C11: =('2_EPS計算'!E8*(1+0.1)*(('1_輸入區'!D19+-0.03)-'1_輸入區'!D20)*(1+'1_輸入區'!D21)*(1-'1_輸入區'!D22))/'1_輸入區'!$B$6 -> 125.11032 | D11: =('2_EPS計算'!E8*(1+0.1)*(('1_輸入區'!D19+-0.015)-'1_輸入區'!D20)*(1+'1_輸入區'!D21)*(1-'1_輸入區'!D22))/'1_輸入區'!$B$6 -> 132.61693 | E11: =('2_EPS計算'!E8*(1+0.1)*(('1_輸入區'!D19+0)-'1_輸入區'!D20)*(1+'1_輸入區'!D21)*(1-'1_輸入區'!D22))/'1_輸入區'!$B$6 -> 140.12355 | F11: =('2_EPS計算'!E8*(1+0.1)*(('1_輸入區'!D19+0.015)-'1_輸入區'!D20)*(1+'1_輸入區'!D21)*(1-'1_輸入區'!D22))/'1_輸入區'!$B$6 -> 147.63017 | G11: =('2_EPS計算'!E8*(1+0.1)*(('1_輸入區'!D19+0.03)-'1_輸入區'!D20)*(1+'1_輸入區'!D21)*(1-'1_輸入區'!D22))/'1_輸入區'!$B$6 -> 155.13679 | H11: =('2_EPS計算'!E8*(1+0.1)*(('1_輸入區'!D19+0.05)-'1_輸入區'!D20)*(1+'1_輸入區'!D21)*(1-'1_輸入區'!D22))/'1_輸入區'!$B$6 -> 165.14562
A12: =SUMPRODUCT('1_輸入區'!B12:B15,'1_輸入區'!E12:E15)/SUM('1_輸入區'!B12:B15)+0.15 -> 0.67099868 | B12: =('2_EPS計算'!E8*(1+0.15)*(('1_輸入區'!D19+-0.05)-'1_輸入區'!D20)*(1+'1_輸入區'!D21)*(1-'1_輸入區'!D22))/'1_輸入區'!$B$6 -> 120.33338 | C12: =('2_EPS計算'!E8*(1+0.15)*(('1_輸入區'!D19+-0.03)-'1_輸入區'!D20)*(1+'1_輸入區'!D21)*(1-'1_輸入區'!D22))/'1_輸入區'!$B$6 -> 130.79715 | D12: =('2_EPS計算'!E8*(1+0.15)*(('1_輸入區'!D19+-0.015)-'1_輸入區'!D20)*(1+'1_輸入區'!D21)*(1-'1_輸入區'!D22))/'1_輸入區'!$B$6 -> 138.64498 | E12: =('2_EPS計算'!E8*(1+0.15)*(('1_輸入區'!D19+0)-'1_輸入區'!D20)*(1+'1_輸入區'!D21)*(1-'1_輸入區'!D22))/'1_輸入區'!$B$6 -> 146.49281 | F12: =('2_EPS計算'!E8*(1+0.15)*(('1_輸入區'!D19+0.015)-'1_輸入區'!D20)*(1+'1_輸入區'!D21)*(1-'1_輸入區'!D22))/'1_輸入區'!$B$6 -> 154.34063 | G12: =('2_EPS計算'!E8*(1+0.15)*(('1_輸入區'!D19+0.03)-'1_輸入區'!D20)*(1+'1_輸入區'!D21)*(1-'1_輸入區'!D22))/'1_輸入區'!$B$6 -> 162.18846 | H12: =('2_EPS計算'!E8*(1+0.15)*(('1_輸入區'!D19+0.05)-'1_輸入區'!D20)*(1+'1_輸入區'!D21)*(1-'1_輸入區'!D22))/'1_輸入區'!$B$6 -> 172.65224
A15: 矩陣B：2028E EPS × PE → 目標價（綠＝高於現價，紅＝低於現價）
A17: EPS\PE | B17: 25 | C17: 35 | D17: 45 | E17: 47.5 | F17: 50 | G17: 60 | H17: 70
A18: =A6 -> 0.37099868 | B18: =D6*B17 -> 2561.918 | C18: =D6*C17 -> 3586.6853 | D18: =D6*D17 -> 4611.4525 | E18: =D6*E17 -> 4867.6443 | F18: =D6*F17 -> 5123.8361 | G18: =D6*G17 -> 6148.6033 | H18: =D6*H17 -> 7173.3705
A19: =A7 -> 0.42099868 | B19: =D7*B17 -> 2712.6191 | C19: =D7*C17 -> 3797.6668 | D19: =D7*D17 -> 4882.7144 | E19: =D7*E17 -> 5153.9763 | F19: =D7*F17 -> 5425.2382 | G19: =D7*G17 -> 6510.2859 | H19: =D7*H17 -> 7595.3335
A20: =A8 -> 0.47099868 | B20: =D8*B17 -> 2863.3202 | C20: =D8*C17 -> 4008.6482 | D20: =D8*D17 -> 5153.9763 | E20: =D8*E17 -> 5440.3083 | F20: =D8*F17 -> 5726.6403 | G20: =D8*G17 -> 6871.9684 | H20: =D8*H17 -> 8017.2965
A21: =A9 -> 0.52099868 | B21: =D9*B17 -> 3014.0212 | C21: =D9*C17 -> 4219.6297 | D21: =D9*D17 -> 5425.2382 | E21: =D9*E17 -> 5726.6403 | F21: =D9*F17 -> 6028.0425 | G21: =D9*G17 -> 7233.651 | H21: =D9*H17 -> 8439.2594
A22: =A10 -> 0.57099868 | B22: =D10*B17 -> 3164.7223 | C22: =D10*C17 -> 4430.6112 | D22: =D10*D17 -> 5696.5001 | E22: =D10*E17 -> 6012.9724 | F22: =D10*F17 -> 6329.4446 | G22: =D10*G17 -> 7595.3335 | H22: =D10*H17 -> 8861.2224
A23: =A11 -> 0.62099868 | B23: =D11*B17 -> 3315.4234 | C23: =D11*C17 -> 4641.5927 | D23: =D11*D17 -> 5967.762 | E23: =D11*E17 -> 6299.3044 | F23: =D11*F17 -> 6630.8467 | G23: =D11*G17 -> 7957.016 | H23: =D11*H17 -> 9283.1854
A24: =A12 -> 0.67099868 | B24: =D12*B17 -> 3466.1244 | C24: =D12*C17 -> 4852.5742 | D24: =D12*D17 -> 6239.0239 | E24: =D12*E17 -> 6585.6364 | F24: =D12*F17 -> 6932.2488 | G24: =D12*G17 -> 8318.6986 | H24: =D12*H17 -> 9705.1484

Sheet 4_情境與檢核
A1: 三情境目標價 + 機率加權 + 隱含成長率檢核
A3: 情境 | B3: 機率 | C3: 2028E EPS | D3: 情境PE | E3: 目標價 | F3: vs 現價
A4: ='1_輸入區'!A34 -> 樂觀 | B4: ='1_輸入區'!B34 -> 0.25 | C4: ='2_EPS計算'!E17*(1+'1_輸入區'!C34) -> 151.67929 | D4: ='1_輸入區'!E34 -> 65 | E4: =C4*D4 -> 9859.1537 | F4: =E4/'1_輸入區'!$B$5-1 -> 5.2797157
A5: ='1_輸入區'!A35 -> 基本 | B5: ='1_輸入區'!B35 -> 0.45 | C5: ='2_EPS計算'!E17*(1+'1_輸入區'!C35) -> 126.39941 | D5: ='1_輸入區'!E35 -> 47.5 | E5: =C5*D5 -> 6003.9718 | F5: =E5/'1_輸入區'!$B$5-1 -> 2.8241859
A6: ='1_輸入區'!A36 -> 保守 | B6: ='1_輸入區'!B36 -> 0.3 | C6: ='2_EPS計算'!E17*(1+'1_輸入區'!C36) -> 44.239792 | D6: ='1_輸入區'!E36 -> 27.5 | E6: =C6*D6 -> 1216.5943 | F6: =E6/'1_輸入區'!$B$5-1 -> -0.22509918
A7: 機率加權目標價 | E7: =SUMPRODUCT(B4:B6,E4:E6) -> 5531.554 | F7: =E7/'1_輸入區'!$B$5-1 -> 2.5232828
A9: 現況本益比基準對照組（不含重評假設，僅反映EPS成長）
A10: 用途：情境目標價已內含PE重評（現況本益比→22-26x），此組固定用現況PE，隔離「純獲利成長」帶來的目標價，供交叉比對
A11: 年度 | B11: EPS | C11: 現況PE基準 | D11: 目標價（不重評） | E11: vs 現價
A12: 2026E | B12: ='2_EPS計算'!C17 -> 34.257982 | C12: ='1_輸入區'!$B$30 -> 113.44 | D12: =B12*C12 -> 3886.2255 | E12: =D12/'1_輸入區'!$B$5-1 -> 1.4753029
A13: 2027E | B13: ='2_EPS計算'!D17 -> 71.122384 | C13: ='1_輸入區'!$B$30 -> 113.44 | D13: =B13*C13 -> 8068.1232 | E13: =D13/'1_輸入區'!$B$5-1 -> 4.138932
A14: 2028E | B14: ='2_EPS計算'!E17 -> 126.39941 | C14: ='1_輸入區'!$B$30 -> 113.44 | D14: =B14*C14 -> 14338.749 | E14: =D14/'1_輸入區'!$B$5-1 -> 8.132961
A16: 隱含成長率檢核（現價反推）
A17: 股價隱含年化成長率 | B17: =('1_輸入區'!$B$5/('1_輸入區'!$B$27*'1_輸入區'!$B$8))^(1/'1_輸入區'!$B$28)-1 -> 0.95087822
A18: 產業平均成長率 | B18: ='1_輸入區'!$B$29 -> 0.19
A19: 隱含成長率 / 產業平均 | B19: =B17/B18 -> 5.0046222
A20: 判讀 | B20: =IF(B19>1.5,"🔴 隱含成長率遠高於產業，估值偏樂觀",IF(B19<0.7,"🟢 隱含成長率低於產業，可能低估","🟡 隱含成長率與產業相近，估值合理")) -> 🔴 隱含成長率遠高於產業，估值偏樂觀
