Workbook

Sheet 0_變量總覽
A1: 估值變量確認總覽 — 聯茂（6213）
A2: 報告日期：20260807｜本表為唯讀摘要，實際輸入請至「1_輸入區」修改
A4: 變量 | B4: 採用值 | C4: 來源 | D4: 影響方向
A5: 現價 | B5: 389.0 元 | C5: Yahoo Finance 2026/08/07 收盤 389.0 元（6 個交易日 +47.9%，52週 88.7~396.0） | D5: 估值基準
A6: 基期EPS | B6: 4.16 元（2025） | C6: 2025 年度 EPS 4.16 元（TWSE 公告） | D6: 估值基準
A7: 傳統/中低階 CCL（FR4~M4） 成長率 | B7: 42% / 49% / 13% | C7: 2025A 佔比約 71.5%（236.65 億）。成長率經反解校準 | D7: 營收→EPS
A8: M6（通用伺服器主流） 成長率 | B8: 84% / 107% / 19% | C8: 2025A 佔比約 22%（72.82 億）。PCIe Gen5→Gen6 平台升級＋泰國廠 | D8: 營收→EPS
A9: M7 以上（AI/LEO/交換機/ASIC） 成長率 | B9: 251% / 219% / 32% | C9: 2025A 佔比約 6.5%（21.51 億）。Starlink＋M7 佔比續升＋Google ASIC 27H2 | D9: 營收→EPS
A10: 毛利率路徑 | B10: 21.8% / 27.5% / 29.2% | C10: ★26Q2 實際 22.02%。2026 年化 21.82%（含 Q1 的 11.42%）。2027-2028 沿用 v12 團隊自建階梯 27.47%／29.17%，向公司口徑「E布緩解後 30% 可達成」靠攏 | D10: EPS
A11: 目標PE區間 | B11: 12.0x - 18.0x | C11: ★團隊自建版 2027E EPS 43.11 元遠高於共識 22.69 元。EPS 基數已內含高成長，PE 不應重複計價，故目標 PE 帶（12~18x）刻意低於共識對齊版（18~25x） | D11: 目標價
A12: 現況PE基準 | B12: 30.3x | C12: 389.0 ÷ 26E 法人共識 EPS 12.82 = 30.3x（優分析共識 20260807） | D12: 對照組
A13: 產業平均成長率 | B13: 20% | C13: 高速 CCL 同業（台光電/台燿）中期 EPS 成長推估 | D13: 隱含成長率檢核
A14: ★校準聲明（20260807 修正） | B14: 本表產品線營收經反解校準，年營收與 EPS 已與損益表預估 xlsx 完全一致 | C14: ★前一版敏感度表存在系統性缺陷：CONFIG 的 product_lines 係憑估填入，未驗證是否能重現損益模型，導致算出的 EPS 路徑高於模型 30~47%，連帶目標價全部灌水。本版以損益模型的年化毛利率/費用率/業外率/有效稅率（含少數股權）直接代入，並用 brentq 反解各產品線成長率使年營收精確命中模型值。稅率欄位為「所得稅＋少數股權」之合併有效率，故已內含歸母比例稀釋。 | D14: 估值方法修正
A15: ★本表＝【團隊自建版】，與共識對齊版並列 | B15: 2026E 16.73／2027E 43.11／2028E 55.56 元 | C15: 另一份 `聯茂_6213_估值敏感度_共識對齊版_20260807.xlsx` 為共識路徑（24.74／27.92）。兩版 2026 年完全相同，2027 年差 18.4 元，其中約 95% 來自營收假設、僅約 5% 來自三率。Wallace 20260807 裁示雙版並存、不預設單一錨點 | D15: 損益模型 v14 雙分頁
... A18: 賠率警語 | B18: 8/02 版 263 元 → 8/07 收 389 元，6 個交易日 +47.9% | C18: ★現價對 2026E 16.73 元為 23.3x。證據在變好、賠率同步變差——這個結論在兩個版本下都成立 | D18: 投資幕僚長判讀

Sheet 1_輸入區
A1: 估值輸入區 — 聯茂（6213）
A2: 報告日期 20260807｜藍字黃底＝可自行改動，改動後全表即時重算
A4: ① 基本資料
A5: 現價（元） | B5: 389 | C5: 來源：Yahoo Finance 2026/08/07 收盤 389.0 元（6 個交易日 +47.9%，52週 88.7~396.0）
A6: 在外流通股數（億股） | B6: 3.635 | C6: 來源：26Q2 財報 EPS 3.52 與歸母淨利 12.79 億回推 ≈3.635 億股
A7: 基期年度 | B7: 2025
A8: 基期 EPS（元） | B8: 4.16 | C8: 來源：2025 年度 EPS 4.16 元（TWSE 公告）
A10: ② 營收假設（億元）
A11: 產品線 | B11: 2025基期營收 | C11: 2026 成長率 | D11: 2027 成長率 | E11: 2028 成長率 | F11: 來源備註
A12: 傳統/中低階 CCL（FR4~M4） | B12: 236.65 | C12: 0.4187 | D12: 0.4875 | E12: 0.1289 | F12: 來源：2025A 佔比約 71.5%（236.65 億）。成長率經反解校準
A13: M6（通用伺服器主流） | B13: 72.82 | C13: 0.8374 | D13: 1.0725 | E13: 0.1933 | F13: 來源：2025A 佔比約 22%（72.82 億）。PCIe Gen5→Gen6 平台升級＋泰國廠
A14: M7 以上（AI/LEO/交換機/ASIC） | B14: 21.51 | C14: 2.5123 | D14: 2.1938 | E14: 0.3221 | F14: 來源：2025A 佔比約 6.5%（21.51 億）。Starlink＋M7 佔比續升＋Google ASIC 27H2
A16: ③ 利潤率假設
A17: 項目 | B17: 2026 | C17: 2027 | D17: 2028 | E17: 來源備註
A18: 毛利率 | B18: 0.2182 | C18: 0.2747 | D18: 0.2917 | E18: 來源：★26Q2 實際 22.02%。2026 年化 21.82%（含 Q1 的 11.42%）。2027-2028 沿用 v12 團隊自建階梯 27.47%／29.17%，向公司口徑「E布緩解後 30% 可達成」靠攏
A19: 營業費用率 | B19: 0.06 | C19: 0.056 | D19: 0.055 | E19: 來源：★26Q2 實際費用率 5.99%（Q1 6.78%）。年化值取自損益模型（兩版相同）
A20: 業外收支/營收 | B20: 0.0019 | C20: 0.0012 | D20: 0.001 | E20: 來源：26Q2 業外 -0.14 億；後續中性推估
A21: 有效稅率 | B21: 0.3032 | C21: 0.3 | D21: 0.3 | E21: 來源：★26Q1 實際 34.8%、26Q2 實際 30.24%；後續 30%。年化值取自損益模型（歸母比例 1.0，無少數股權稀釋）
A23: ④ 估值假設
A24: 目標 PE 下緣 | B24: 12 | C24: 來源：★團隊自建版 2027E EPS 43.11 元遠高於共識 22.69 元。EPS 基數已內含高成長，PE 不應重複計價，故目標 PE 帶（12~18x）刻意低於共識對齊版（18~25x）
A25: 目標 PE 上緣 | B25: 18
A26: 出場 PE（隱含成長率檢核） | B26: 15
A27: 評估年數 N | B27: 2
A28: 產業平均 EPS 成長率 | B28: 0.2 | C28: 來源：高速 CCL 同業（台光電/台燿）中期 EPS 成長推估
A29: 現況本益比基準（不含重評，對照用） | B29: 30.3 | C29: 來源：389.0 ÷ 26E 法人共識 EPS 12.82 = 30.3x（優分析共識 20260807）
A31: ⑤ 情境調整（相對基本假設）
A32: 情境 | B32: 機率 | C32: 營收成長率調整 | D32: 毛利率調整 | E32: 情境 PE | F32: 情境說明
A33: 樂觀 | B33: 0.15 | C33: 0.08 | D33: 0.015 | E33: 20 | F33: Starlink／泰國廠／M7 佔比／Google ASIC 四條線全部按期兌現，2028 年 M9 提前貢獻
A34: 基本 | B34: 0.25 | C34: 0 | D34: 0 | E34: 15 | F34: 完全依 v12 團隊自建路徑：2027 營收 1,018.0 億（YoY +86.8%）、EPS 43.11 元。★這是本表最需要被質疑的一條
A35: 保守（向共識收斂） | B35: 0.4 | C35: -0.39 | D35: -0.013 | E35: 15 | F35: ★機率最高：2027 營收由 1,018 億收斂至共識 619.3 億（-39%），對應共識對齊版 EPS 24.74 元。四條線任一延後即落入此情境
A36: 循環見頂 | B36: 0.2 | C36: -0.55 | D36: -0.04 | E36: 11 | F36: ★共識 2028E EPS 由 2027 的 22.69 降至 14.80（-34.8%），已明示市場預期 2028 年反轉

Sheet 2_EPS計算
A1: EPS 計算（全公式，勿直接改本表——請改 1_輸入區）
A3: 項目 | B3: 2025A | C3: 2026E | D3: 2027E | E3: 2028E
A4: 傳統/中低階 CCL（FR4~M4） 營收 | B4: ='1_輸入區'!B12 | C4: =B4*(1+'1_輸入區'!C12) | D4: =C4*(1+'1_輸入區'!D12) | E4: =D4*(1+'1_輸入區'!E12)
A5: M6（通用伺服器主流） 營收 | B5: ='1_輸入區'!B13 | C5: =B5*(1+'1_輸入區'!C13) | D5: =C5*(1+'1_輸入區'!D13) | E5: =D5*(1+'1_輸入區'!E13)
A6: M7 以上（AI/LEO/交換機/ASIC） 營收 | B6: ='1_輸入區'!B14 | C6: =B6*(1+'1_輸入區'!C14) | D6: =C6*(1+'1_輸入區'!D14) | E6: =D6*(1+'1_輸入區'!E14)
A7: 總營收（億元） | B7: =SUM(B4:B6) | C7: =SUM(C4:C6) | D7: =SUM(D4:D6) | E7: =SUM(E4:E6)
A8: 毛利率 | B8: n/a | C8: ='1_輸入區'!B18 | D8: ='1_輸入區'!C18 | E8: ='1_輸入區'!D18
A9: 營業毛利（億元） | B9: n/a | C9: =C7*C8 | D9: =D7*D8 | E9: =E7*E8
A10: 營業費用率 | B10: n/a | C10: ='1_輸入區'!B19 | D10: ='1_輸入區'!C19 | E10: ='1_輸入區'!D19
A11: 營業利益（億元） | B11: n/a | C11: =C9-C7*C10 | D11: =D9-D7*D10 | E11: =E9-E7*E10
A12: 業外收支率 | B12: n/a | C12: ='1_輸入區'!B20 | D12: ='1_輸入區'!C20 | E12: ='1_輸入區'!D20
A13: 稅前淨利（億元） | B13: n/a | C13: =C11+C7*C12 | D13: =D11+D7*D12 | E13: =E11+E7*E12
A14: 有效稅率 | B14: n/a | C14: ='1_輸入區'!B21 | D14: ='1_輸入區'!C21 | E14: ='1_輸入區'!D21
A15: 稅後淨利（億元） | B15: n/a | C15: =C13*(1-C14) | D15: =D13*(1-D14) | E15: =E13*(1-E14)
A16: EPS（元） | B16: ='1_輸入區'!$B$8 | C16: =C15/'1_輸入區'!$B$6 | D16: =D15/'1_輸入區'!$B$6 | E16: =E15/'1_輸入區'!$B$6
A18: 目標價（PE下緣） | C18: =C16*'1_輸入區'!$B$24 | D18: =D16*'1_輸入區'!$B$24 | E18: =E16*'1_輸入區'!$B$24
A19: 目標價（PE上緣） | C19: =C16*'1_輸入區'!$B$25 | D19: =D16*'1_輸入區'!$B$25 | E19: =E16*'1_輸入區'!$B$25

Sheet 3_敏感度
A1: 敏感度矩陣（以最後預測年度為基準）
A3: 矩陣A：2028E 總營收YoY × 毛利率 → EPS
A5: 營收YoY\毛利率 | B5: ='1_輸入區'!D18+-0.05 | C5: ='1_輸入區'!D18+-0.03 | D5: ='1_輸入區'!D18+-0.015 | E5: ='1_輸入區'!D18+0.0 | F5: ='1_輸入區'!D18+0.015 | G5: ='1_輸入區'!D18+0.03 | H5: ='1_輸入區'!D18+0.05
A6: =SUMPRODUCT('1_輸入區'!B12:B14,'1_輸入區'!E12:E14)/SUM('1_輸入區'!B12:B14)+-0.15 | B6: =('2_EPS計算'!E7*(1+-0.15)*(('1_輸入區'!D18+-0.05)-'1_輸入區'!D19)*(1+'1_輸入區'!D20)*(1-'1_輸入區'!D21))/'1_輸入區'!$B$6 | C6: =('2_EPS計算'!E7*(1+-0.15)*(('1_輸入區'!D18+-0.03)-'1_輸入區'!D19)*(1+'1_輸入區'!D20)*(1-'1_輸入區'!D21))/'1_輸入區'!$B$6 | D6: =('2_EPS計算'!E7*(1+-0.15)*(('1_輸入區'!D18+-0.015)-'1_輸入區'!D19)*(1+'1_輸入區'!D20)*(1-'1_輸入區'!D21))/'1_輸入區'!$B$6 | E6: =('2_EPS計算'!E7*(1+-0.15)*(('1_輸入區'!D18+0.0)-'1_輸入區'!D19)*(1+'1_輸入區'!D20)*(1-'1_輸入區'!D21))/'1_輸入區'!$B$6 | F6: =('2_EPS計算'!E7*(1+-0.15)*(('1_輸入區'!D18+0.015)-'1_輸入區'!D19)*(1+'1_輸入區'!D20)*(1-'1_輸入區'!D21))/'1_輸入區'!$B$6 | G6: =('2_EPS計算'!E7*(1+-0.15)*(('1_輸入區'!D18+0.03)-'1_輸入區'!D19)*(1+'1_輸入區'!D20)*(1-'1_輸入區'!D21))/'1_輸入區'!$B$6 | H6: =('2_EPS計算'!E7*(1+-0.15)*(('1_輸入區'!D18+0.05)-'1_輸入區'!D19)*(1+'1_輸入區'!D20)*(1-'1_輸入區'!D21))/'1_輸入區'!$B$6
A7: =SUMPRODUCT('1_輸入區'!B12:B14,'1_輸入區'!E12:E14)/SUM('1_輸入區'!B12:B14)+-0.1 | B7: =('2_EPS計算'!E7*(1+-0.1)*(('1_輸入區'!D18+-0.05)-'1_輸入區'!D19)*(1+'1_輸入區'!D20)*(1-'1_輸入區'!D21))/'1_輸入區'!$B$6 | C7: =('2_EPS計算'!E7*(1+-0.1)*(('1_輸入區'!D18+-0.03)-'1_輸入區'!D19)*(1+'1_輸入區'!D20)*(1-'1_輸入區'!D21))/'1_輸入區'!$B$6 | D7: =('2_EPS計算'!E7*(1+-0.1)*(('1_輸入區'!D18+-0.015)-'1_輸入區'!D19)*(1+'1_輸入區'!D20)*(1-'1_輸入區'!D21))/'1_輸入區'!$B$6 | E7: =('2_EPS計算'!E7*(1+-0.1)*(('1_輸入區'!D18+0.0)-'1_輸入區'!D19)*(1+'1_輸入區'!D20)*(1-'1_輸入區'!D21))/'1_輸入區'!$B$6 | F7: =('2_EPS計算'!E7*(1+-0.1)*(('1_輸入區'!D18+0.015)-'1_輸入區'!D19)*(1+'1_輸入區'!D20)*(1-'1_輸入區'!D21))/'1_輸入區'!$B$6 | G7: =('2_EPS計算'!E7*(1+-0.1)*(('1_輸入區'!D18+0.03)-'1_輸入區'!D19)*(1+'1_輸入區'!D20)*(1-'1_輸入區'!D21))/'1_輸入區'!$B$6 | H7: =('2_EPS計算'!E7*(1+-0.1)*(('1_輸入區'!D18+0.05)-'1_輸入區'!D19)*(1+'1_輸入區'!D20)*(1-'1_輸入區'!D21))/'1_輸入區'!$B$6
A8: =SUMPRODUCT('1_輸入區'!B12:B14,'1_輸入區'!E12:E14)/SUM('1_輸入區'!B12:B14)+-0.05 | B8: =('2_EPS計算'!E7*(1+-0.05)*(('1_輸入區'!D18+-0.05)-'1_輸入區'!D19)*(1+'1_輸入區'!D20)*(1-'1_輸入區'!D21))/'1_輸入區'!$B$6 | C8: =('2_EPS計算'!E7*(1+-0.05)*(('1_輸入區'!D18+-0.03)-'1_輸入區'!D19)*(1+'1_輸入區'!D20)*(1-'1_輸入區'!D21))/'1_輸入區'!$B$6 | D8: =('2_EPS計算'!E7*(1+-0.05)*(('1_輸入區'!D18+-0.015)-'1_輸入區'!D19)*(1+'1_輸入區'!D20)*(1-'1_輸入區'!D21))/'1_輸入區'!$B$6 | E8: =('2_EPS計算'!E7*(1+-0.05)*(('1_輸入區'!D18+0.0)-'1_輸入區'!D19)*(1+'1_輸入區'!D20)*(1-'1_輸入區'!D21))/'1_輸入區'!$B$6 | F8: =('2_EPS計算'!E7*(1+-0.05)*(('1_輸入區'!D18+0.015)-'1_輸入區'!D19)*(1+'1_輸入區'!D20)*(1-'1_輸入區'!D21))/'1_輸入區'!$B$6 | G8: =('2_EPS計算'!E7*(1+-0.05)*(('1_輸入區'!D18+0.03)-'1_輸入區'!D19)*(1+'1_輸入區'!D20)*(1-'1_輸入區'!D21))/'1_輸入區'!$B$6 | H8: =('2_EPS計算'!E7*(1+-0.05)*(('1_輸入區'!D18+0.05)-'1_輸入區'!D19)*(1+'1_輸入區'!D20)*(1-'1_輸入區'!D21))/'1_輸入區'!$B$6
A9: =SUMPRODUCT('1_輸入區'!B12:B14,'1_輸入區'!E12:E14)/SUM('1_輸入區'!B12:B14)+0.0 | B9: =('2_EPS計算'!E7*(1+0.0)*(('1_輸入區'!D18+-0.05)-'1_輸入區'!D19)*(1+'1_輸入區'!D20)*(1-'1_輸入區'!D21))/'1_輸入區'!$B$6 | C9: =('2_EPS計算'!E7*(1+0.0)*(('1_輸入區'!D18+-0.03)-'1_輸入區'!D19)*(1+'1_輸入區'!D20)*(1-'1_輸入區'!D21))/'1_輸入區'!$B$6 | D9: =('2_EPS計算'!E7*(1+0.0)*(('1_輸入區'!D18+-0.015)-'1_輸入區'!D19)*(1+'1_輸入區'!D20)*(1-'1_輸入區'!D21))/'1_輸入區'!$B$6 | E9: =('2_EPS計算'!E7*(1+0.0)*(('1_輸入區'!D18+0.0)-'1_輸入區'!D19)*(1+'1_輸入區'!D20)*(1-'1_輸入區'!D21))/'1_輸入區'!$B$6 | F9: =('2_EPS計算'!E7*(1+0.0)*(('1_輸入區'!D18+0.015)-'1_輸入區'!D19)*(1+'1_輸入區'!D20)*(1-'1_輸入區'!D21))/'1_輸入區'!$B$6 | G9: =('2_EPS計算'!E7*(1+0.0)*(('1_輸入區'!D18+0.03)-'1_輸入區'!D19)*(1+'1_輸入區'!D20)*(1-'1_輸入區'!D21))/'1_輸入區'!$B$6 | H9: =('2_EPS計算'!E7*(1+0.0)*(('1_輸入區'!D18+0.05)-'1_輸入區'!D19)*(1+'1_輸入區'!D20)*(1-'1_輸入區'!D21))/'1_輸入區'!$B$6
A10: =SUMPRODUCT('1_輸入區'!B12:B14,'1_輸入區'!E12:E14)/SUM('1_輸入區'!B12:B14)+0.05 | B10: =('2_EPS計算'!E7*(1+0.05)*(('1_輸入區'!D18+-0.05)-'1_輸入區'!D19)*(1+'1_輸入區'!D20)*(1-'1_輸入區'!D21))/'1_輸入區'!$B$6 | C10: =('2_EPS計算'!E7*(1+0.05)*(('1_輸入區'!D18+-0.03)-'1_輸入區'!D19)*(1+'1_輸入區'!D20)*(1-'1_輸入區'!D21))/'1_輸入區'!$B$6 | D10: =('2_EPS計算'!E7*(1+0.05)*(('1_輸入區'!D18+-0.015)-'1_輸入區'!D19)*(1+'1_輸入區'!D20)*(1-'1_輸入區'!D21))/'1_輸入區'!$B$6 | E10: =('2_EPS計算'!E7*(1+0.05)*(('1_輸入區'!D18+0.0)-'1_輸入區'!D19)*(1+'1_輸入區'!D20)*(1-'1_輸入區'!D21))/'1_輸入區'!$B$6 | F10: =('2_EPS計算'!E7*(1+0.05)*(('1_輸入區'!D18+0.015)-'1_輸入區'!D19)*(1+'1_輸入區'!D20)*(1-'1_輸入區'!D21))/'1_輸入區'!$B$6 | G10: =('2_EPS計算'!E7*(1+0.05)*(('1_輸入區'!D18+0.03)-'1_輸入區'!D19)*(1+'1_輸入區'!D20)*(1-'1_輸入區'!D21))/'1_輸入區'!$B$6 | H10: =('2_EPS計算'!E7*(1+0.05)*(('1_輸入區'!D18+0.05)-'1_輸入區'!D19)*(1+'1_輸入區'!D20)*(1-'1_輸入區'!D21))/'1_輸入區'!$B$6
A11: =SUMPRODUCT('1_輸入區'!B12:B14,'1_輸入區'!E12:E14)/SUM('1_輸入區'!B12:B14)+0.1 | B11: =('2_EPS計算'!E7*(1+0.1)*(('1_輸入區'!D18+-0.05)-'1_輸入區'!D19)*(1+'1_輸入區'!D20)*(1-'1_輸入區'!D21))/'1_輸入區'!$B$6 | C11: =('2_EPS計算'!E7*(1+0.1)*(('1_輸入區'!D18+-0.03)-'1_輸入區'!D19)*(1+'1_輸入區'!D20)*(1-'1_輸入區'!D21))/'1_輸入區'!$B$6 | D11: =('2_EPS計算'!E7*(1+0.1)*(('1_輸入區'!D18+-0.015)-'1_輸入區'!D19)*(1+'1_輸入區'!D20)*(1-'1_輸入區'!D21))/'1_輸入區'!$B$6 | E11: =('2_EPS計算'!E7*(1+0.1)*(('1_輸入區'!D18+0.0)-'1_輸入區'!D19)*(1+'1_輸入區'!D20)*(1-'1_輸入區'!D21))/'1_輸入區'!$B$6 | F11: =('2_EPS計算'!E7*(1+0.1)*(('1_輸入區'!D18+0.015)-'1_輸入區'!D19)*(1+'1_輸入區'!D20)*(1-'1_輸入區'!D21))/'1_輸入區'!$B$6 | G11: =('2_EPS計算'!E7*(1+0.1)*(('1_輸入區'!D18+0.03)-'1_輸入區'!D19)*(1+'1_輸入區'!D20)*(1-'1_輸入區'!D21))/'1_輸入區'!$B$6 | H11: =('2_EPS計算'!E7*(1+0.1)*(('1_輸入區'!D18+0.05)-'1_輸入區'!D19)*(1+'1_輸入區'!D20)*(1-'1_輸入區'!D21))/'1_輸入區'!$B$6
A12: =SUMPRODUCT('1_輸入區'!B12:B14,'1_輸入區'!E12:E14)/SUM('1_輸入區'!B12:B14)+0.15 | B12: =('2_EPS計算'!E7*(1+0.15)*(('1_輸入區'!D18+-0.05)-'1_輸入區'!D19)*(1+'1_輸入區'!D20)*(1-'1_輸入區'!D21))/'1_輸入區'!$B$6 | C12: =('2_EPS計算'!E7*(1+0.15)*(('1_輸入區'!D18+-0.03)-'1_輸入區'!D19)*(1+'1_輸入區'!D20)*(1-'1_輸入區'!D21))/'1_輸入區'!$B$6 | D12: =('2_EPS計算'!E7*(1+0.15)*(('1_輸入區'!D18+-0.015)-'1_輸入區'!D19)*(1+'1_輸入區'!D20)*(1-'1_輸入區'!D21))/'1_輸入區'!$B$6 | E12: =('2_EPS計算'!E7*(1+0.15)*(('1_輸入區'!D18+0.0)-'1_輸入區'!D19)*(1+'1_輸入區'!D20)*(1-'1_輸入區'!D21))/'1_輸入區'!$B$6 | F12: =('2_EPS計算'!E7*(1+0.15)*(('1_輸入區'!D18+0.015)-'1_輸入區'!D19)*(1+'1_輸入區'!D20)*(1-'1_輸入區'!D21))/'1_輸入區'!$B$6 | G12: =('2_EPS計算'!E7*(1+0.15)*(('1_輸入區'!D18+0.03)-'1_輸入區'!D19)*(1+'1_輸入區'!D20)*(1-'1_輸入區'!D21))/'1_輸入區'!$B$6 | H12: =('2_EPS計算'!E7*(1+0.15)*(('1_輸入區'!D18+0.05)-'1_輸入區'!D19)*(1+'1_輸入區'!D20)*(1-'1_輸入區'!D21))/'1_輸入區'!$B$6
A15: 矩陣B：2028E EPS × PE → 目標價（綠＝高於現價，紅＝低於現價）
A17: EPS\PE | B17: 16 | C17: 20 | D17: 25 | E17: 27 | F17: 30 | G17: 32 | H17: 40
A18: =A6 | B18: =D6*B17 | C18: =D6*C17 | D18: =D6*D17 | E18: =D6*E17 | F18: =D6*F17 | G18: =D6*G17 | H18: =D6*H17
A19: =A7 | B19: =D7*B17 | C19: =D7*C17 | D19: =D7*D17 | E19: =D7*E17 | F19: =D7*F17 | G19: =D7*G17 | H19: =D7*H17
A20: =A8 | B20: =D8*B17 | C20: =D8*C17 | D20: =D8*D17 | E20: =D8*E17 | F20: =D8*F17 | G20: =D8*G17 | H20: =D8*H17
A21: =A9 | B21: =D9*B17 | C21: =D9*C17 | D21: =D9*D17 | E21: =D9*E17 | F21: =D9*F17 | G21: =D9*G17 | H21: =D9*H17
A22: =A10 | B22: =D10*B17 | C22: =D10*C17 | D22: =D10*D17 | E22: =D10*E17 | F22: =D10*F17 | G22: =D10*G17 | H22: =D10*H17
A23: =A11 | B23: =D11*B17 | C23: =D11*C17 | D23: =D11*D17 | E23: =D11*E17 | F23: =D11*F17 | G23: =D11*G17 | H23: =D11*H17
A24: =A12 | B24: =D12*B17 | C24: =D12*C17 | D24: =D12*D17 | E24: =D12*E17 | F24: =D12*F17 | G24: =D12*G17 | H24: =D12*H17

Sheet 4_情境與檢核
A1: 三情境目標價 + 機率加權 + 隱含成長率檢核
A3: 情境 | B3: 機率 | C3: 2028E EPS | D3: 情境PE | E3: 目標價 | F3: vs 現價
A4: ='1_輸入區'!A33 | B4: ='1_輸入區'!B33 | C4: =('2_EPS計算'!E7*(1+'1_輸入區'!C33)*(('2_EPS計算'!E8+'1_輸入區'!D33)-'2_EPS計算'!E10+'2_EPS計算'!E12)*(1-'2_EPS計算'!E14))/'1_輸入區'!$B$6 | D4: ='1_輸入區'!E33 | E4: =C4*D4 | F4: =E4/'1_輸入區'!$B$5-1
A5: ='1_輸入區'!A34 | B5: ='1_輸入區'!B34 | C5: =('2_EPS計算'!E7*(1+'1_輸入區'!C34)*(('2_EPS計算'!E8+'1_輸入區'!D34)-'2_EPS計算'!E10+'2_EPS計算'!E12)*(1-'2_EPS計算'!E14))/'1_輸入區'!$B$6 | D5: ='1_輸入區'!E34 | E5: =C5*D5 | F5: =E5/'1_輸入區'!$B$5-1
A6: ='1_輸入區'!A35 | B6: ='1_輸入區'!B35 | C6: =('2_EPS計算'!E7*(1+'1_輸入區'!C35)*(('2_EPS計算'!E8+'1_輸入區'!D35)-'2_EPS計算'!E10+'2_EPS計算'!E12)*(1-'2_EPS計算'!E14))/'1_輸入區'!$B$6 | D6: ='1_輸入區'!E35 | E6: =C6*D6 | F6: =E6/'1_輸入區'!$B$5-1
A7: ='1_輸入區'!A36 | B7: ='1_輸入區'!B36 | C7: =('2_EPS計算'!E7*(1+'1_輸入區'!C36)*(('2_EPS計算'!E8+'1_輸入區'!D36)-'2_EPS計算'!E10+'2_EPS計算'!E12)*(1-'2_EPS計算'!E14))/'1_輸入區'!$B$6 | D7: ='1_輸入區'!E36 | E7: =C7*D7 | F7: =E7/'1_輸入區'!$B$5-1
A8: 機率加權目標價 | E8: =SUMPRODUCT(B4:B7,E4:E7) | F8: =E8/'1_輸入區'!$B$5-1
A10: 現況本益比基準對照組（不含重評假設，僅反映EPS成長）
A11: 用途：情境目標價已內含PE重評（現況本益比→22-26x），此組固定用現況PE，隔離「純獲利成長」帶來的目標價，供交叉比對
A12: 年度 | B12: EPS | C12: 現況PE基準 | D12: 目標價（不重評） | E12: vs 現價
A13: 2026E | B13: ='2_EPS計算'!C16 | C13: ='1_輸入區'!$B$29 | D13: =B13*C13 | E13: =D13/'1_輸入區'!$B$5-1
A14: 2027E | B14: ='2_EPS計算'!D16 | C14: ='1_輸入區'!$B$29 | D14: =B14*C14 | E14: =D14/'1_輸入區'!$B$5-1
A15: 2028E | B15: ='2_EPS計算'!E16 | C15: ='1_輸入區'!$B$29 | D15: =B15*C15 | E15: =D15/'1_輸入區'!$B$5-1
A17: 隱含成長率檢核（現價反推）
A18: 股價隱含年化成長率 | B18: =('1_輸入區'!$B$5/('1_輸入區'!$B$26*'1_輸入區'!$B$8))^(1/'1_輸入區'!$B$27)-1
A19: 產業平均成長率 | B19: ='1_輸入區'!$B$28
A20: 隱含成長率 / 產業平均 | B20: =B18/B19
A21: 判讀 | B21: =IF(B20>1.5,"🔴 隱含成長率遠高於產業，估值偏樂觀",IF(B20<0.7,"🟢 隱含成長率低於產業，可能低估","🟡 隱含成長率與產業相近，估值合理"))
